{"defaults":{"_name":"framerate"},"$schema":"http:\/\/json-schema.org\/draft-04\/schema#","name":"framerate","groups":[{"id":"filter.framerate.standard","class":"standard","properties":[{"parameter":"fps","control":{"type":"string","value":"50"},"id":"filter.framerate.standard.fps"},{"parameter":"interp_start","control":{"singleStep":1,"maximum":255,"type":"integer","minimum":0,"value":0},"id":"filter.framerate.standard.interp_start"},{"parameter":"interp_end","control":{"singleStep":1,"maximum":255,"type":"integer","minimum":0,"value":0},"id":"filter.framerate.standard.interp_end"},{"parameter":"scene","control":{"singleStep":0.10000000149011612,"maximum":2147483648,"type":"float","minimum":0,"value":8.199999809265137},"id":"filter.framerate.standard.scene"},{"parameter":"flags","control":{"type":"combobox","items":[{"value":"scene_change_detect"},{"value":"scd"}],"selectedIndex":1},"id":"filter.framerate.standard.flags"}]}],"id":"filter.framerate","type":"video"}