{"defaults":{"_name":"convolution"},"$schema":"http:\/\/json-schema.org\/draft-04\/schema#","name":"convolution","groups":[{"id":"filter.convolution.standard","class":"standard","properties":[{"parameter":"0m","control":{"type":"string","value":"0 0 0 0 1 0 0 0 0"},"id":"filter.convolution.standard.0m"},{"parameter":"1m","control":{"type":"string","value":"0 0 0 0 1 0 0 0 0"},"id":"filter.convolution.standard.1m"},{"parameter":"2m","control":{"type":"string","value":"0 0 0 0 1 0 0 0 0"},"id":"filter.convolution.standard.2m"},{"parameter":"3m","control":{"type":"string","value":"0 0 0 0 1 0 0 0 0"},"id":"filter.convolution.standard.3m"},{"parameter":"0rdiv","control":{"singleStep":0.10000000149011612,"maximum":2147483648,"type":"float","minimum":0,"value":0},"id":"filter.convolution.standard.0rdiv"},{"parameter":"1rdiv","control":{"singleStep":0.10000000149011612,"maximum":2147483648,"type":"float","minimum":0,"value":0},"id":"filter.convolution.standard.1rdiv"},{"parameter":"2rdiv","control":{"singleStep":0.10000000149011612,"maximum":2147483648,"type":"float","minimum":0,"value":0},"id":"filter.convolution.standard.2rdiv"},{"parameter":"3rdiv","control":{"singleStep":0.10000000149011612,"maximum":2147483648,"type":"float","minimum":0,"value":0},"id":"filter.convolution.standard.3rdiv"},{"parameter":"0bias","control":{"singleStep":0.10000000149011612,"maximum":2147483648,"type":"float","minimum":0,"value":0},"id":"filter.convolution.standard.0bias"},{"parameter":"1bias","control":{"singleStep":0.10000000149011612,"maximum":2147483648,"type":"float","minimum":0,"value":0},"id":"filter.convolution.standard.1bias"},{"parameter":"2bias","control":{"singleStep":0.10000000149011612,"maximum":2147483648,"type":"float","minimum":0,"value":0},"id":"filter.convolution.standard.2bias"},{"parameter":"3bias","control":{"singleStep":0.10000000149011612,"maximum":2147483648,"type":"float","minimum":0,"value":0},"id":"filter.convolution.standard.3bias"},{"parameter":"0mode","control":{"singleStep":1,"maximum":2,"type":"integer","minimum":0,"value":0},"id":"filter.convolution.standard.0mode"},{"parameter":"1mode","control":{"singleStep":1,"maximum":2,"type":"integer","minimum":0,"value":0},"id":"filter.convolution.standard.1mode"},{"parameter":"2mode","control":{"singleStep":1,"maximum":2,"type":"integer","minimum":0,"value":0},"id":"filter.convolution.standard.2mode"},{"parameter":"3mode","control":{"type":"combobox","items":[{"value":"square"},{"value":"row"},{"value":"column"}],"selectedIndex":0},"id":"filter.convolution.standard.3mode"}]}],"id":"filter.convolution","type":"video"}