{"defaults":{"_name":"dynaudnorm"},"$schema":"http:\/\/json-schema.org\/draft-04\/schema#","name":"dynaudnorm","groups":[{"id":"filter.dynaudnorm.standard","class":"standard","properties":[{"parameter":"f","control":{"singleStep":1,"maximum":8000,"type":"integer","minimum":10,"value":10},"id":"filter.dynaudnorm.standard.f"},{"parameter":"g","control":{"singleStep":1,"maximum":301,"type":"integer","minimum":3,"value":3},"id":"filter.dynaudnorm.standard.g"},{"parameter":"p","control":{"singleStep":0.10000000149011612,"maximum":1,"type":"float","minimum":0,"value":0.949999988079071},"id":"filter.dynaudnorm.standard.p"},{"parameter":"m","control":{"singleStep":0.10000000149011612,"maximum":100,"type":"float","minimum":1,"value":10},"id":"filter.dynaudnorm.standard.m"},{"parameter":"r","control":{"singleStep":0.10000000149011612,"maximum":1,"type":"float","minimum":0,"value":0},"id":"filter.dynaudnorm.standard.r"},{"parameter":"n","control":{"type":"boolean","value":true},"id":"filter.dynaudnorm.standard.n"},{"parameter":"c","control":{"type":"boolean","value":false},"id":"filter.dynaudnorm.standard.c"},{"parameter":"b","control":{"type":"boolean","value":false},"id":"filter.dynaudnorm.standard.b"},{"parameter":"s","control":{"singleStep":0.10000000149011612,"maximum":30,"type":"float","minimum":0,"value":0},"id":"filter.dynaudnorm.standard.s"}]}],"id":"filter.dynaudnorm","type":"audio"}