{"defaults":{"_name":"afade"},"$schema":"http:\/\/json-schema.org\/draft-04\/schema#","name":"afade","groups":[{"id":"filter.afade.standard","class":"standard","properties":[{"parameter":"type","control":{"type":"combobox","items":[{"value":"in"},{"value":"out"}],"selectedIndex":0},"id":"filter.afade.standard.type"},{"parameter":"start_sample","control":{"singleStep":1,"maximum":-2147483648,"type":"integer","minimum":0,"value":0},"id":"filter.afade.standard.start_sample"},{"parameter":"nb_samples","control":{"singleStep":1,"maximum":-2147483648,"type":"integer","minimum":1,"value":1},"id":"filter.afade.standard.nb_samples"},{"parameter":"start_time","control":{"singleStep":1,"maximum":-2147483648,"type":"integer","minimum":0,"value":0},"id":"filter.afade.standard.start_time"},{"parameter":"duration","control":{"singleStep":1,"maximum":-2147483648,"type":"integer","minimum":0,"value":0},"id":"filter.afade.standard.duration"},{"parameter":"curve","control":{"type":"combobox","items":[{"value":"tri"},{"value":"qsin"},{"value":"esin"},{"value":"hsin"},{"value":"log"},{"value":"ipar"},{"value":"qua"},{"value":"cub"},{"value":"squ"},{"value":"cbr"},{"value":"par"},{"value":"exp"},{"value":"iqsin"},{"value":"ihsin"},{"value":"dese"},{"value":"desi"},{"value":"losi"},{"value":"nofade"}],"selectedIndex":0},"id":"filter.afade.standard.curve"}]}],"id":"filter.afade","type":"audio"}