{"$schema":"http:\/\/json-schema.org\/draft-04\/schema#","description":"An OpenAddresses source","additionalProperties":false,"title":"Source","type":"object","definitions":{"_88function_remove_prefix":{"description":"remove_prefix function definition","additionalProperties":false,"type":"object","properties":{"___field":{"type":"string"},"___function":{"type":"string","enum":["remove_prefix"]},"___field_to_remove":{"type":"string"}},"required":["function","field","field_to_remove"]},"_88function_regexp":{"description":"regexp function definition","additionalProperties":false,"type":"object","properties":{"___field":{"type":"string"},"___function":{"type":"string","enum":["regexp"]},"___replace":{"type":"string"},"___pattern":{"format":"string","type":"string"}},"required":["function","field","pattern"]},"_88function_format":{"description":"format function definition","additionalProperties":false,"type":"object","properties":{"___fields":{"minItems":1,"type":"array","items":{"type":"string"}},"___format":{"type":"string"},"___function":{"type":"string","enum":["format"]}},"required":["function","fields","format"]},"_88base_conform_field_value":{"oneOf":[{"type":"null"},{"type":"string"},{"minItems":1,"type":"array","items":{"type":"string"}}],"description":"convenience definition for one of null, string, or string array"},"_88function_remove_postfix":{"description":"remove_postfix function definition","additionalProperties":false,"type":"object","properties":{"___field":{"type":"string"},"___function":{"type":"string","enum":["remove_postfix"]},"___field_to_remove":{"type":"string"}},"required":["function","field","field_to_remove"]},"_88function_postfixed_street":{"description":"postfixed_street function definition","additionalProperties":false,"type":"object","properties":{"___field":{"type":"string"},"___function":{"type":"string","enum":["postfixed_street"]}},"required":["function","field"]},"_88coverage":{"type":"object","properties":{"___state":{"type":"string"},"___province":{"type":"string"},"___country":{"type":"string"},"___geometry":{"$eref":{"description":"A geometry is a GeoJSON object where the type member's value is one of the following strings: `Point`, `MultiPoint`, `LineString`, `MultiLineString`, `Polygon`, `MultiPolygon`, or `GeometryCollection`.","title":"Geometry","properties":{"___type":{"enum":["Point","MultiPoint","LineString","MultiLineString","Polygon","MultiPolygon","GeometryCollection"]}}}},"___county":{"type":"string"},"___city":{"type":"string"}},"required":["country"]},"_88license":{"type":"object","properties":{"___text":{"type":"string"},"___attribution":{"type":"boolean"},"___share-alike":{"type":"boolean"},"___url":{"format":"uri","type":"string"},"___attribution name":{"type":"string"}}},"_88function_join":{"description":"join function definition","additionalProperties":false,"type":"object","properties":{"___fields":{"minItems":1,"type":"array","items":{"type":"string"}},"___separator":{"type":"string"},"___function":{"type":"string","enum":["join"]}},"required":["function","fields"]},"_88conform":{"description":"top-level conform object definition","additionalProperties":false,"type":"object","properties":{"___lat":{"oneOf":[{"type":"null"},{"type":"string"},{"$eref":{"description":"regexp function definition","additionalProperties":false,"type":"object","properties":{"___field":{"type":"string"},"___function":{"type":"string","enum":["regexp"]},"___replace":{"type":"string"},"___pattern":{"format":"string","type":"string"}},"required":["function","field","pattern"]}}],"description":"latitude value for the address row, only applies to CSV sources"},"___type":{"type":"string","enum":["geojson","shapefile","shapefile-polygon","gdb","xml","csv"]},"___postcode":{"oneOf":[{"$eref":{"oneOf":[{"type":"null"},{"type":"string"},{"minItems":1,"type":"array","items":{"type":"string"}}],"description":"convenience definition for one of null, string, or string array"}},{"$eref":{"description":"regexp function definition","additionalProperties":false,"type":"object","properties":{"___field":{"type":"string"},"___function":{"type":"string","enum":["regexp"]},"___replace":{"type":"string"},"___pattern":{"format":"string","type":"string"}},"required":["function","field","pattern"]}},{"$eref":{"description":"remove_prefix function definition","additionalProperties":false,"type":"object","properties":{"___field":{"type":"string"},"___function":{"type":"string","enum":["remove_prefix"]},"___field_to_remove":{"type":"string"}},"required":["function","field","field_to_remove"]}},{"$eref":{"description":"remove_postfix function definition","additionalProperties":false,"type":"object","properties":{"___field":{"type":"string"},"___function":{"type":"string","enum":["remove_postfix"]},"___field_to_remove":{"type":"string"}},"required":["function","field","field_to_remove"]}},{"$eref":{"description":"join function definition","additionalProperties":false,"type":"object","properties":{"___fields":{"minItems":1,"type":"array","items":{"type":"string"}},"___separator":{"type":"string"},"___function":{"type":"string","enum":["join"]}},"required":["function","fields"]}},{"$eref":{"description":"format function definition","additionalProperties":false,"type":"object","properties":{"___fields":{"minItems":1,"type":"array","items":{"type":"string"}},"___format":{"type":"string"},"___function":{"type":"string","enum":["format"]}},"required":["function","fields","format"]}}],"description":"the postcode for the address row"},"___layer":{"oneOf":[{"type":"integer"},{"type":"string"}],"description":"specifies a layer to use in the GDB"},"___file":{"type":"string"},"___accuracy":{"description":"https:\/\/github.com\/openaddresses\/openaddresses\/blob\/master\/CONTRIBUTING.md#accuracy","maximum":5,"exclusiveMinimum":true,"type":"integer","minimum":0},"___addrtype":{"type":"string"},"___lon":{"oneOf":[{"type":"null"},{"type":"string"},{"$eref":{"description":"regexp function definition","additionalProperties":false,"type":"object","properties":{"___field":{"type":"string"},"___function":{"type":"string","enum":["regexp"]},"___replace":{"type":"string"},"___pattern":{"format":"string","type":"string"}},"required":["function","field","pattern"]}}],"description":"longitude value for the address row, only applies to CSV sources"},"___district":{"oneOf":[{"$eref":{"oneOf":[{"type":"null"},{"type":"string"},{"minItems":1,"type":"array","items":{"type":"string"}}],"description":"convenience definition for one of null, string, or string array"}},{"$eref":{"description":"regexp function definition","additionalProperties":false,"type":"object","properties":{"___field":{"type":"string"},"___function":{"type":"string","enum":["regexp"]},"___replace":{"type":"string"},"___pattern":{"format":"string","type":"string"}},"required":["function","field","pattern"]}},{"$eref":{"description":"remove_prefix function definition","additionalProperties":false,"type":"object","properties":{"___field":{"type":"string"},"___function":{"type":"string","enum":["remove_prefix"]},"___field_to_remove":{"type":"string"}},"required":["function","field","field_to_remove"]}},{"$eref":{"description":"remove_postfix function definition","additionalProperties":false,"type":"object","properties":{"___field":{"type":"string"},"___function":{"type":"string","enum":["remove_postfix"]},"___field_to_remove":{"type":"string"}},"required":["function","field","field_to_remove"]}},{"$eref":{"description":"join function definition","additionalProperties":false,"type":"object","properties":{"___fields":{"minItems":1,"type":"array","items":{"type":"string"}},"___separator":{"type":"string"},"___function":{"type":"string","enum":["join"]}},"required":["function","fields"]}},{"$eref":{"description":"format function definition","additionalProperties":false,"type":"object","properties":{"___fields":{"minItems":1,"type":"array","items":{"type":"string"}},"___format":{"type":"string"},"___function":{"type":"string","enum":["format"]}},"required":["function","fields","format"]}}],"description":"the county for the address row"},"___encoding":{"type":"string"},"___srs":{"regex":"EPSG:[0-9]+","type":"string"},"___number":{"oneOf":[{"$eref":{"oneOf":[{"type":"null"},{"type":"string"},{"minItems":1,"type":"array","items":{"type":"string"}}],"description":"convenience definition for one of null, string, or string array"}},{"$eref":{"description":"regexp function definition","additionalProperties":false,"type":"object","properties":{"___field":{"type":"string"},"___function":{"type":"string","enum":["regexp"]},"___replace":{"type":"string"},"___pattern":{"format":"string","type":"string"}},"required":["function","field","pattern"]}},{"$eref":{"description":"prefixed_number function definition","additionalProperties":false,"type":"object","properties":{"___field":{"type":"string"},"___function":{"type":"string","enum":["prefixed_number"]}},"required":["function","field"]}},{"$eref":{"description":"remove_prefix function definition","additionalProperties":false,"type":"object","properties":{"___field":{"type":"string"},"___function":{"type":"string","enum":["remove_prefix"]},"___field_to_remove":{"type":"string"}},"required":["function","field","field_to_remove"]}},{"$eref":{"description":"remove_postfix function definition","additionalProperties":false,"type":"object","properties":{"___field":{"type":"string"},"___function":{"type":"string","enum":["remove_postfix"]},"___field_to_remove":{"type":"string"}},"required":["function","field","field_to_remove"]}},{"$eref":{"description":"join function definition","additionalProperties":false,"type":"object","properties":{"___fields":{"minItems":1,"type":"array","items":{"type":"string"}},"___separator":{"type":"string"},"___function":{"type":"string","enum":["join"]}},"required":["function","fields"]}},{"$eref":{"description":"format function definition","additionalProperties":false,"type":"object","properties":{"___fields":{"minItems":1,"type":"array","items":{"type":"string"}},"___format":{"type":"string"},"___function":{"type":"string","enum":["format"]}},"required":["function","fields","format"]}}],"description":"the house number for the address row"},"___skiplines":{"type":"integer","minimum":1},"___street":{"oneOf":[{"$eref":{"oneOf":[{"type":"null"},{"type":"string"},{"minItems":1,"type":"array","items":{"type":"string"}}],"description":"convenience definition for one of null, string, or string array"}},{"$eref":{"description":"regexp function definition","additionalProperties":false,"type":"object","properties":{"___field":{"type":"string"},"___function":{"type":"string","enum":["regexp"]},"___replace":{"type":"string"},"___pattern":{"format":"string","type":"string"}},"required":["function","field","pattern"]}},{"$eref":{"description":"postfixed_street function definition","additionalProperties":false,"type":"object","properties":{"___field":{"type":"string"},"___function":{"type":"string","enum":["postfixed_street"]}},"required":["function","field"]}},{"$eref":{"description":"remove_prefix function definition","additionalProperties":false,"type":"object","properties":{"___field":{"type":"string"},"___function":{"type":"string","enum":["remove_prefix"]},"___field_to_remove":{"type":"string"}},"required":["function","field","field_to_remove"]}},{"$eref":{"description":"remove_postfix function definition","additionalProperties":false,"type":"object","properties":{"___field":{"type":"string"},"___function":{"type":"string","enum":["remove_postfix"]},"___field_to_remove":{"type":"string"}},"required":["function","field","field_to_remove"]}},{"$eref":{"description":"join function definition","additionalProperties":false,"type":"object","properties":{"___fields":{"minItems":1,"type":"array","items":{"type":"string"}},"___separator":{"type":"string"},"___function":{"type":"string","enum":["join"]}},"required":["function","fields"]}},{"$eref":{"description":"format function definition","additionalProperties":false,"type":"object","properties":{"___fields":{"minItems":1,"type":"array","items":{"type":"string"}},"___format":{"type":"string"},"___function":{"type":"string","enum":["format"]}},"required":["function","fields","format"]}}],"description":"the street\/road for the address row"},"___csvsplit":{"type":"string"},"___headers":{"type":"integer","minimum":-1},"___notes":{"type":"string"},"___id":{"oneOf":[{"$eref":{"oneOf":[{"type":"null"},{"type":"string"},{"minItems":1,"type":"array","items":{"type":"string"}}],"description":"convenience definition for one of null, string, or string array"}},{"$eref":{"description":"regexp function definition","additionalProperties":false,"type":"object","properties":{"___field":{"type":"string"},"___function":{"type":"string","enum":["regexp"]},"___replace":{"type":"string"},"___pattern":{"format":"string","type":"string"}},"required":["function","field","pattern"]}},{"$eref":{"description":"remove_prefix function definition","additionalProperties":false,"type":"object","properties":{"___field":{"type":"string"},"___function":{"type":"string","enum":["remove_prefix"]},"___field_to_remove":{"type":"string"}},"required":["function","field","field_to_remove"]}},{"$eref":{"description":"remove_postfix function definition","additionalProperties":false,"type":"object","properties":{"___field":{"type":"string"},"___function":{"type":"string","enum":["remove_postfix"]},"___field_to_remove":{"type":"string"}},"required":["function","field","field_to_remove"]}},{"$eref":{"description":"join function definition","additionalProperties":false,"type":"object","properties":{"___fields":{"minItems":1,"type":"array","items":{"type":"string"}},"___separator":{"type":"string"},"___function":{"type":"string","enum":["join"]}},"required":["function","fields"]}},{"$eref":{"description":"format function definition","additionalProperties":false,"type":"object","properties":{"___fields":{"minItems":1,"type":"array","items":{"type":"string"}},"___format":{"type":"string"},"___function":{"type":"string","enum":["format"]}},"required":["function","fields","format"]}}],"description":"unique identifier for the address row"},"___unit":{"oneOf":[{"$eref":{"oneOf":[{"type":"null"},{"type":"string"},{"minItems":1,"type":"array","items":{"type":"string"}}],"description":"convenience definition for one of null, string, or string array"}},{"$eref":{"description":"regexp function definition","additionalProperties":false,"type":"object","properties":{"___field":{"type":"string"},"___function":{"type":"string","enum":["regexp"]},"___replace":{"type":"string"},"___pattern":{"format":"string","type":"string"}},"required":["function","field","pattern"]}},{"$eref":{"description":"remove_prefix function definition","additionalProperties":false,"type":"object","properties":{"___field":{"type":"string"},"___function":{"type":"string","enum":["remove_prefix"]},"___field_to_remove":{"type":"string"}},"required":["function","field","field_to_remove"]}},{"$eref":{"description":"remove_postfix function definition","additionalProperties":false,"type":"object","properties":{"___field":{"type":"string"},"___function":{"type":"string","enum":["remove_postfix"]},"___field_to_remove":{"type":"string"}},"required":["function","field","field_to_remove"]}},{"$eref":{"description":"join function definition","additionalProperties":false,"type":"object","properties":{"___fields":{"minItems":1,"type":"array","items":{"type":"string"}},"___separator":{"type":"string"},"___function":{"type":"string","enum":["join"]}},"required":["function","fields"]}},{"$eref":{"description":"format function definition","additionalProperties":false,"type":"object","properties":{"___fields":{"minItems":1,"type":"array","items":{"type":"string"}},"___format":{"type":"string"},"___function":{"type":"string","enum":["format"]}},"required":["function","fields","format"]}}],"description":"the suite\/unit\/apartment for the address row"},"___city":{"oneOf":[{"$eref":{"oneOf":[{"type":"null"},{"type":"string"},{"minItems":1,"type":"array","items":{"type":"string"}}],"description":"convenience definition for one of null, string, or string array"}},{"$eref":{"description":"regexp function definition","additionalProperties":false,"type":"object","properties":{"___field":{"type":"string"},"___function":{"type":"string","enum":["regexp"]},"___replace":{"type":"string"},"___pattern":{"format":"string","type":"string"}},"required":["function","field","pattern"]}},{"$eref":{"description":"remove_prefix function definition","additionalProperties":false,"type":"object","properties":{"___field":{"type":"string"},"___function":{"type":"string","enum":["remove_prefix"]},"___field_to_remove":{"type":"string"}},"required":["function","field","field_to_remove"]}},{"$eref":{"description":"remove_postfix function definition","additionalProperties":false,"type":"object","properties":{"___field":{"type":"string"},"___function":{"type":"string","enum":["remove_postfix"]},"___field_to_remove":{"type":"string"}},"required":["function","field","field_to_remove"]}},{"$eref":{"description":"join function definition","additionalProperties":false,"type":"object","properties":{"___fields":{"minItems":1,"type":"array","items":{"type":"string"}},"___separator":{"type":"string"},"___function":{"type":"string","enum":["join"]}},"required":["function","fields"]}},{"$eref":{"description":"format function definition","additionalProperties":false,"type":"object","properties":{"___fields":{"minItems":1,"type":"array","items":{"type":"string"}},"___format":{"type":"string"},"___function":{"type":"string","enum":["format"]}},"required":["function","fields","format"]}}],"description":"the city\/locality for the address row"},"___region":{"oneOf":[{"$eref":{"oneOf":[{"type":"null"},{"type":"string"},{"minItems":1,"type":"array","items":{"type":"string"}}],"description":"convenience definition for one of null, string, or string array"}},{"$eref":{"description":"regexp function definition","additionalProperties":false,"type":"object","properties":{"___field":{"type":"string"},"___function":{"type":"string","enum":["regexp"]},"___replace":{"type":"string"},"___pattern":{"format":"string","type":"string"}},"required":["function","field","pattern"]}},{"$eref":{"description":"remove_prefix function definition","additionalProperties":false,"type":"object","properties":{"___field":{"type":"string"},"___function":{"type":"string","enum":["remove_prefix"]},"___field_to_remove":{"type":"string"}},"required":["function","field","field_to_remove"]}},{"$eref":{"description":"remove_postfix function definition","additionalProperties":false,"type":"object","properties":{"___field":{"type":"string"},"___function":{"type":"string","enum":["remove_postfix"]},"___field_to_remove":{"type":"string"}},"required":["function","field","field_to_remove"]}},{"$eref":{"description":"join function definition","additionalProperties":false,"type":"object","properties":{"___fields":{"minItems":1,"type":"array","items":{"type":"string"}},"___separator":{"type":"string"},"___function":{"type":"string","enum":["join"]}},"required":["function","fields"]}},{"$eref":{"description":"format function definition","additionalProperties":false,"type":"object","properties":{"___fields":{"minItems":1,"type":"array","items":{"type":"string"}},"___format":{"type":"string"},"___function":{"type":"string","enum":["format"]}},"required":["function","fields","format"]}}],"description":"the state\/province for the address row"}},"required":["number","street"]},"_88function_prefixed_number":{"description":"prefixed_number function definition","additionalProperties":false,"type":"object","properties":{"___field":{"type":"string"},"___function":{"type":"string","enum":["prefixed_number"]}},"required":["function","field"]}},"properties":{"___language":{"pattern":"[a-zA-Z]{2}","type":"string"},"___conform":{"$eref":{"description":"top-level conform object definition","additionalProperties":false,"type":"object","properties":{"___lat":{"oneOf":[{"type":"null"},{"type":"string"},{"$ref":"#\/definitions\/function_regexp"}],"description":"latitude value for the address row, only applies to CSV sources"},"___type":{"type":"string","enum":["geojson","shapefile","shapefile-polygon","gdb","xml","csv"]},"___postcode":{"oneOf":[{"$ref":"#\/definitions\/base_conform_field_value"},{"$ref":"#\/definitions\/function_regexp"},{"$ref":"#\/definitions\/function_remove_prefix"},{"$ref":"#\/definitions\/function_remove_postfix"},{"$ref":"#\/definitions\/function_join"},{"$ref":"#\/definitions\/function_format"}],"description":"the postcode for the address row"},"___layer":{"oneOf":[{"type":"integer"},{"type":"string"}],"description":"specifies a layer to use in the GDB"},"___file":{"type":"string"},"___accuracy":{"description":"https:\/\/github.com\/openaddresses\/openaddresses\/blob\/master\/CONTRIBUTING.md#accuracy","maximum":5,"exclusiveMinimum":true,"type":"integer","minimum":0},"___addrtype":{"type":"string"},"___lon":{"oneOf":[{"type":"null"},{"type":"string"},{"$ref":"#\/definitions\/function_regexp"}],"description":"longitude value for the address row, only applies to CSV sources"},"___district":{"oneOf":[{"$ref":"#\/definitions\/base_conform_field_value"},{"$ref":"#\/definitions\/function_regexp"},{"$ref":"#\/definitions\/function_remove_prefix"},{"$ref":"#\/definitions\/function_remove_postfix"},{"$ref":"#\/definitions\/function_join"},{"$ref":"#\/definitions\/function_format"}],"description":"the county for the address row"},"___encoding":{"type":"string"},"___srs":{"regex":"EPSG:[0-9]+","type":"string"},"___number":{"oneOf":[{"$ref":"#\/definitions\/base_conform_field_value"},{"$ref":"#\/definitions\/function_regexp"},{"$ref":"#\/definitions\/function_prefixed_number"},{"$ref":"#\/definitions\/function_remove_prefix"},{"$ref":"#\/definitions\/function_remove_postfix"},{"$ref":"#\/definitions\/function_join"},{"$ref":"#\/definitions\/function_format"}],"description":"the house number for the address row"},"___skiplines":{"type":"integer","minimum":1},"___street":{"oneOf":[{"$ref":"#\/definitions\/base_conform_field_value"},{"$ref":"#\/definitions\/function_regexp"},{"$ref":"#\/definitions\/function_postfixed_street"},{"$ref":"#\/definitions\/function_remove_prefix"},{"$ref":"#\/definitions\/function_remove_postfix"},{"$ref":"#\/definitions\/function_join"},{"$ref":"#\/definitions\/function_format"}],"description":"the street\/road for the address row"},"___csvsplit":{"type":"string"},"___headers":{"type":"integer","minimum":-1},"___notes":{"type":"string"},"___id":{"oneOf":[{"$ref":"#\/definitions\/base_conform_field_value"},{"$ref":"#\/definitions\/function_regexp"},{"$ref":"#\/definitions\/function_remove_prefix"},{"$ref":"#\/definitions\/function_remove_postfix"},{"$ref":"#\/definitions\/function_join"},{"$ref":"#\/definitions\/function_format"}],"description":"unique identifier for the address row"},"___unit":{"oneOf":[{"$ref":"#\/definitions\/base_conform_field_value"},{"$ref":"#\/definitions\/function_regexp"},{"$ref":"#\/definitions\/function_remove_prefix"},{"$ref":"#\/definitions\/function_remove_postfix"},{"$ref":"#\/definitions\/function_join"},{"$ref":"#\/definitions\/function_format"}],"description":"the suite\/unit\/apartment for the address row"},"___city":{"oneOf":[{"$ref":"#\/definitions\/base_conform_field_value"},{"$ref":"#\/definitions\/function_regexp"},{"$ref":"#\/definitions\/function_remove_prefix"},{"$ref":"#\/definitions\/function_remove_postfix"},{"$ref":"#\/definitions\/function_join"},{"$ref":"#\/definitions\/function_format"}],"description":"the city\/locality for the address row"},"___region":{"oneOf":[{"$ref":"#\/definitions\/base_conform_field_value"},{"$ref":"#\/definitions\/function_regexp"},{"$ref":"#\/definitions\/function_remove_prefix"},{"$ref":"#\/definitions\/function_remove_postfix"},{"$ref":"#\/definitions\/function_join"},{"$ref":"#\/definitions\/function_format"}],"description":"the state\/province for the address row"}},"required":["number","street"]}},"___attribution":{"type":"string"},"___skip":{"type":"boolean"},"___email":{"format":"email","type":"string"},"___year":{"oneOf":[{"type":"string"},{"type":"number"}]},"___license":{"oneOf":[{"type":"string"},{"$eref":{"type":"object","properties":{"___text":{"type":"string"},"___attribution":{"type":"boolean"},"___share-alike":{"type":"boolean"},"___url":{"format":"uri","type":"string"},"___attribution name":{"type":"string"}}}}]},"___type":{"type":"string","enum":["http","ftp","ESRI"]},"___note":{"oneOf":[{"type":"string"},{"type":"object"}]},"___coverage":{"$eref":{"type":"object","properties":{"___state":{"type":"string"},"___province":{"type":"string"},"___country":{"type":"string"},"___geometry":{"$ref":"http:\/\/json.schemastore.org\/geojson#\/definitions\/geometry"},"___county":{"type":"string"},"___city":{"type":"string"}},"required":["country"]}},"___website":{"type":"string"},"___compression":{"type":"string","enum":["zip"]},"___data":{"type":"string"}},"required":["type","data","coverage"]}