{"$schema":"http:\/\/json-schema.org\/draft-04\/schema#","description":"Generated from kata\/spec\/fixtures\/examples\/detect_optional.json with shasum 0857611ca5599619cc5094a8906403dcf64a8abc","type":"object","properties":{"___name":{"type":"string"},"___price":{"type":"number"},"___tags":{"minItems":1,"uniqueItems":true,"type":"array","items":{"type":"object","properties":{"___home":{"type":"string"},"___color":{"type":"string"}},"required":["home"]}},"___hash":{"minItems":1,"uniqueItems":true,"type":"array","items":{"type":"object","properties":{"___deep_required":{"type":"string"},"___deep_optional":{"type":"string"}},"required":["deep_required"]}},"___id":{"type":"integer"}},"required":["id","name","price","tags","hash"]}