{"$schema":"http:\/\/json-schema.org\/schema#","type":"object","title":"com.apple.mcxprinting","properties":{"___FooterFontSize":{"default":"7","description":"The font size (in points) of the footer","type":"string"},"___UserPrinterList":{"description":"A list of printers to manage. The PPD software must already exist on the target","type":"dict","properties":{"___QueueName":{"description":"The queue name of the printer, must not include spaces or special characters. Not shown to the user.","type":"dict","properties":{"___Option":{"default":{},"description":"Printer Options. A dict of key to value including options normally supplied to lpadmin","type":"dict"},"___DisplayName":{"description":"The display name shown to the user when choosing a printer.","type":"string"},"___Model":{"description":"The printer model usually corresponding to the PPD model name eg 2nd column of `lpinfo -m`.","type":"string"},"___DeviceURI":{"description":"The printer device URI, as would be passed to CUPS eg. lpd:\/\/printer.name\/queue","type":"string"},"___PPDURL":{"description":"The path to the PPD file. Local file URLs should be prefixed with file:\/\/localhost\/","type":"string"},"___PrinterLocked":{"default":false,"description":"The printer requires an administrator password","type":"boolean"},"___Location":{"description":"The printer location","type":"string"}}}}},"___PayloadIdentifier":{"default":"com.apple.mcxprinting","description":"A unique identifier for the payload, dot-delimited.  Usually root PayloadIdentifier+subidentifier","type":"string"},"___PrintFooter":{"description":"Print a page footer including the user name and date","type":"boolean"},"___DefaultPrinter":{"description":"Default Printer Configuration","type":"dict","properties":{"___DisplayName":{"description":"The display name of the Default Printer","type":"string"},"___DeviceURI":{"description":"The device URI of the Default Printer","type":"string"}}},"___PayloadVersion":{"default":1,"description":"The version of the whole configuration profile.","type":"number"},"___AllowLocalPrinters":{"description":"Allow printers that connect directly to user's computer","type":"boolean"},"___PayloadDisplayName":{"default":"Printer Settings","description":"Name of the payload","type":"string"},"___PayloadUUID":{"default":"","pattern":"^[0-9A-Za-z]{8}-[0-9A-Za-z]{4}-[0-9A-Za-z]{4}-[0-9A-Za-z]{4}-[0-9A-Za-z]{12}$","description":"Unique identifier for the payload (format 01234567-89AB-CDEF-0123-456789ABCDEF)","type":"string"},"___PayloadType":{"default":"com.apple.mcxprinting","description":"The type of the payload, a reverse dns string","type":"string"},"___PayloadOrganization":{"description":"This value describes the issuing organization of the profile, as displayed to the user","type":"string"},"___RequireAdminToPrintLocally":{"description":"Require an administrator password to print to locally connected printers","type":"boolean"},"___RequireAdminToAddPrinters":{"description":"Only administrators may modify the printer list","type":"boolean"},"___PayloadDescription":{"default":"Printer Settings","description":"Description of the payload","type":"string"},"___FooterFontName":{"default":"Courier","description":"The name of the font to use for the footer eg. Courier","type":"string"},"___ShowOnlyManagedPrinters":{"description":"Only show printers managed by profiles","type":"boolean"},"___PrintMACAddress":{"description":"Include the MAC address of the user's computer in the footer","type":"boolean"}}}