{"$schema":"http:\/\/json-schema.org\/draft-04\/schema#","type":"object","definitions":{"_88CommandInputSchema":{"type":"object","properties":{"___type":{"anyOf":[{"type":"string","enum":["null"]},{"type":"string","enum":["boolean"]},{"type":"string","enum":["int"]},{"type":"string","enum":["long"]},{"type":"string","enum":["float"]},{"type":"string","enum":["double"]},{"type":"string","enum":["bytes"]},{"type":"string","enum":["string"]},{"type":"string","enum":["File"]},{"$eref":{"type":"object","properties":{"___type":{"anyOf":[{"type":"string","enum":["null"]},{"type":"string","enum":["boolean"]},{"type":"string","enum":["int"]},{"type":"string","enum":["long"]},{"type":"string","enum":["float"]},{"type":"string","enum":["double"]},{"type":"string","enum":["bytes"]},{"type":"string","enum":["string"]},{"type":"string","enum":["File"]},{"$ref":"#\/definitions\/CommandInputSchema"},{"type":"string"},{"$ref":"#\/definitions\/CommandInputMapSchema"},{"$ref":"#\/definitions\/CommandInputArraySchema"},{"$ref":"#\/definitions\/CommandInputRecordSchema"},{"$ref":"#\/definitions\/CommandInputEnumSchema"},{"type":"array","items":{"anyOf":[{"type":"string","enum":["null"]},{"type":"string","enum":["boolean"]},{"type":"string","enum":["int"]},{"type":"string","enum":["long"]},{"type":"string","enum":["float"]},{"type":"string","enum":["double"]},{"type":"string","enum":["bytes"]},{"type":"string","enum":["string"]},{"type":"string","enum":["File"]},{"$ref":"#\/definitions\/CommandInputSchema"},{"type":"string"},{"$ref":"#\/definitions\/CommandInputMapSchema"},{"$ref":"#\/definitions\/CommandInputArraySchema"},{"$ref":"#\/definitions\/CommandInputEnumSchema"},{"$ref":"#\/definitions\/CommandInputRecordSchema"}]}}]},"___inputBinding":{"$ref":"#\/definitions\/CommandLineBinding"}},"required":["type"]}},{"type":"string"},{"$eref":{"type":"object","properties":{"___type":{"type":"string","enum":["map"]},"___inputBinding":{"$ref":"#\/definitions\/CommandLineBinding"},"___values":{"type":"string"}},"required":["type","values"]}},{"$eref":{"type":"object","properties":{"___type":{"type":"string","enum":["array"]},"___items":{"anyOf":[{"type":"string","enum":["null"]},{"type":"string","enum":["boolean"]},{"type":"string","enum":["int"]},{"type":"string","enum":["long"]},{"type":"string","enum":["float"]},{"type":"string","enum":["double"]},{"type":"string","enum":["bytes"]},{"type":"string","enum":["string"]},{"type":"string","enum":["File"]},{"$ref":"#\/definitions\/CommandInputSchema"},{"$ref":"#\/definitions\/CommandInputMapSchema"},{"$ref":"#\/definitions\/CommandInputArraySchema"},{"$ref":"#\/definitions\/CommandInputRecordSchema"},{"$ref":"#\/definitions\/CommandInputEnumSchema"},{"type":"string"},{"type":"array","items":{"anyOf":[{"type":"string","enum":["null"]},{"type":"string","enum":["boolean"]},{"type":"string","enum":["int"]},{"type":"string","enum":["long"]},{"type":"string","enum":["float"]},{"type":"string","enum":["double"]},{"type":"string","enum":["bytes"]},{"type":"string","enum":["string"]},{"type":"string","enum":["File"]},{"$ref":"#\/definitions\/CommandInputSchema"},{"$ref":"#\/definitions\/CommandInputMapSchema"},{"$ref":"#\/definitions\/CommandInputArraySchema"},{"$ref":"#\/definitions\/CommandInputEnumSchema"},{"$ref":"#\/definitions\/CommandInputRecordSchema"},{"type":"string"}]}}]},"___inputBinding":{"$ref":"#\/definitions\/CommandLineBinding"}},"required":["items","type"]}},{"$eref":{"type":"object","properties":{"___fields":{"type":"array","items":{"anyOf":[{"$ref":"#\/definitions\/CommandInputSchema"},{"$ref":"#\/definitions\/CommandInputArraySchema"},{"$ref":"#\/definitions\/CommandInputRecordSchema"},{"$ref":"#\/definitions\/CommandInputEnumSchema"},{"$ref":"#\/definitions\/CommandInputMapSchema"}]}},"___type":{"type":"string","enum":["record"]},"___inputBinding":{"$ref":"#\/definitions\/CommandLineBinding"}},"required":["type","fields"]}},{"$eref":{"type":"object","properties":{"___name":{"type":"string"},"___type":{"type":"string","enum":["enum"]},"___symbols":{"type":"array","items":{"type":"string"}},"___inputBinding":{"$ref":"#\/definitions\/CommandLineBinding"}},"required":["type","symbols","name"]}},{"type":"array","items":{"anyOf":[{"type":"string","enum":["null"]},{"type":"string","enum":["boolean"]},{"type":"string","enum":["int"]},{"type":"string","enum":["long"]},{"type":"string","enum":["float"]},{"type":"string","enum":["double"]},{"type":"string","enum":["bytes"]},{"type":"string","enum":["string"]},{"type":"string","enum":["File"]},{"$eref":{"type":"object","properties":{"___type":{"anyOf":[{"type":"string","enum":["null"]},{"type":"string","enum":["boolean"]},{"type":"string","enum":["int"]},{"type":"string","enum":["long"]},{"type":"string","enum":["float"]},{"type":"string","enum":["double"]},{"type":"string","enum":["bytes"]},{"type":"string","enum":["string"]},{"type":"string","enum":["File"]},{"$ref":"#\/definitions\/CommandInputSchema"},{"type":"string"},{"$ref":"#\/definitions\/CommandInputMapSchema"},{"$ref":"#\/definitions\/CommandInputArraySchema"},{"$ref":"#\/definitions\/CommandInputRecordSchema"},{"$ref":"#\/definitions\/CommandInputEnumSchema"},{"type":"array","items":{"anyOf":[{"type":"string","enum":["null"]},{"type":"string","enum":["boolean"]},{"type":"string","enum":["int"]},{"type":"string","enum":["long"]},{"type":"string","enum":["float"]},{"type":"string","enum":["double"]},{"type":"string","enum":["bytes"]},{"type":"string","enum":["string"]},{"type":"string","enum":["File"]},{"$ref":"#\/definitions\/CommandInputSchema"},{"type":"string"},{"$ref":"#\/definitions\/CommandInputMapSchema"},{"$ref":"#\/definitions\/CommandInputArraySchema"},{"$ref":"#\/definitions\/CommandInputEnumSchema"},{"$ref":"#\/definitions\/CommandInputRecordSchema"}]}}]},"___inputBinding":{"$ref":"#\/definitions\/CommandLineBinding"}},"required":["type"]}},{"type":"string"},{"$eref":{"type":"object","properties":{"___type":{"type":"string","enum":["map"]},"___inputBinding":{"$ref":"#\/definitions\/CommandLineBinding"},"___values":{"type":"string"}},"required":["type","values"]}},{"$eref":{"type":"object","properties":{"___type":{"type":"string","enum":["array"]},"___items":{"anyOf":[{"type":"string","enum":["null"]},{"type":"string","enum":["boolean"]},{"type":"string","enum":["int"]},{"type":"string","enum":["long"]},{"type":"string","enum":["float"]},{"type":"string","enum":["double"]},{"type":"string","enum":["bytes"]},{"type":"string","enum":["string"]},{"type":"string","enum":["File"]},{"$ref":"#\/definitions\/CommandInputSchema"},{"$ref":"#\/definitions\/CommandInputMapSchema"},{"$ref":"#\/definitions\/CommandInputArraySchema"},{"$ref":"#\/definitions\/CommandInputRecordSchema"},{"$ref":"#\/definitions\/CommandInputEnumSchema"},{"type":"string"},{"type":"array","items":{"anyOf":[{"type":"string","enum":["null"]},{"type":"string","enum":["boolean"]},{"type":"string","enum":["int"]},{"type":"string","enum":["long"]},{"type":"string","enum":["float"]},{"type":"string","enum":["double"]},{"type":"string","enum":["bytes"]},{"type":"string","enum":["string"]},{"type":"string","enum":["File"]},{"$ref":"#\/definitions\/CommandInputSchema"},{"$ref":"#\/definitions\/CommandInputMapSchema"},{"$ref":"#\/definitions\/CommandInputArraySchema"},{"$ref":"#\/definitions\/CommandInputEnumSchema"},{"$ref":"#\/definitions\/CommandInputRecordSchema"},{"type":"string"}]}}]},"___inputBinding":{"$ref":"#\/definitions\/CommandLineBinding"}},"required":["items","type"]}},{"$eref":{"type":"object","properties":{"___name":{"type":"string"},"___type":{"type":"string","enum":["enum"]},"___symbols":{"type":"array","items":{"type":"string"}},"___inputBinding":{"$ref":"#\/definitions\/CommandLineBinding"}},"required":["type","symbols","name"]}},{"$eref":{"type":"object","properties":{"___fields":{"type":"array","items":{"anyOf":[{"$ref":"#\/definitions\/CommandInputSchema"},{"$ref":"#\/definitions\/CommandInputArraySchema"},{"$ref":"#\/definitions\/CommandInputRecordSchema"},{"$ref":"#\/definitions\/CommandInputEnumSchema"},{"$ref":"#\/definitions\/CommandInputMapSchema"}]}},"___type":{"type":"string","enum":["record"]},"___inputBinding":{"$ref":"#\/definitions\/CommandLineBinding"}},"required":["type","fields"]}}]}}]},"___inputBinding":{"$eref":{"type":"object","properties":{"___itemSeparator":{"type":["string","null"]},"___loadContents":{"type":"boolean"},"___prefix":{"type":"string"},"___secondaryFiles":{"anyOf":[{"type":"string"},{"$ref":"#\/definitions\/Expression"},{"type":"array","items":{"anyOf":[{"type":"string"},{"$ref":"#\/definitions\/Expression"}]}}]},"___valueFrom":{"anyOf":[{"type":"string"},{"$ref":"#\/definitions\/Expression"}]},"___separate":{"type":"boolean"},"___position":{"type":"number"}}}}},"required":["type"]},"_88ExpressionEngineRequirement":{"type":"object","properties":{"___requirements":{"type":"array","items":{"anyOf":[{"$eref":{"type":"object","properties":{"___dockerOutputDirectory":{"type":"string"},"___class":{"type":"string","enum":["DockerRequirement"]},"___dockerLoad":{"type":"string"},"___dockerFile":{"type":"string"},"___dockerPull":{"type":"string"},"___dockerImageId":{"type":"string"}},"required":["class"]}},{"$eref":{"type":"object","properties":{}}},{"$eref":{"type":"object","properties":{"___fileDef":{"type":"array","items":{"$ref":"#\/definitions\/FileDef"}},"___class":{"type":"string","enum":["CreateFileRequirement"]}},"required":["class","fileDef"]}},{"$eref":{"type":"object","properties":{}}},{"$eref":{"type":"object","properties":{}}},{"$eref":{"type":"object","properties":{}}},{"$eref":{"type":"object","properties":{"___requirements":{"type":"array","items":{"anyOf":[{"$ref":"#\/definitions\/DockerRequirement"},{"$ref":"#\/definitions\/SubworkflowFeatureRequirement"},{"$ref":"#\/definitions\/CreateFileRequirement"},{"$ref":"#\/definitions\/EnvVarRequirement"},{"$ref":"#\/definitions\/ScatterFeatureRequirement"},{"$ref":"#\/definitions\/SchemaDefRequirement"},{"$ref":"#\/definitions\/ExpressionEngineRequirement"}]}},"___class":{"type":"string","enum":["ExpressionEngineRequirement"]},"___engineCommand":{"anyOf":[{"type":"string"},{"type":"array","items":{"type":"string"}}]},"___id":{"type":"string"},"___engineConfig":{"type":"array","items":{"type":"string"}}},"required":["class","id"]}}]}},"___class":{"type":"string","enum":["ExpressionEngineRequirement"]},"___engineCommand":{"anyOf":[{"type":"string"},{"type":"array","items":{"type":"string"}}]},"___id":{"type":"string"},"___engineConfig":{"type":"array","items":{"type":"string"}}},"required":["class","id"]},"_88CommandInputRecordSchema":{"type":"object","properties":{"___fields":{"type":"array","items":{"anyOf":[{"$eref":{"type":"object","properties":{"___type":{"anyOf":[{"type":"string","enum":["null"]},{"type":"string","enum":["boolean"]},{"type":"string","enum":["int"]},{"type":"string","enum":["long"]},{"type":"string","enum":["float"]},{"type":"string","enum":["double"]},{"type":"string","enum":["bytes"]},{"type":"string","enum":["string"]},{"type":"string","enum":["File"]},{"$ref":"#\/definitions\/CommandInputSchema"},{"type":"string"},{"$ref":"#\/definitions\/CommandInputMapSchema"},{"$ref":"#\/definitions\/CommandInputArraySchema"},{"$ref":"#\/definitions\/CommandInputRecordSchema"},{"$ref":"#\/definitions\/CommandInputEnumSchema"},{"type":"array","items":{"anyOf":[{"type":"string","enum":["null"]},{"type":"string","enum":["boolean"]},{"type":"string","enum":["int"]},{"type":"string","enum":["long"]},{"type":"string","enum":["float"]},{"type":"string","enum":["double"]},{"type":"string","enum":["bytes"]},{"type":"string","enum":["string"]},{"type":"string","enum":["File"]},{"$ref":"#\/definitions\/CommandInputSchema"},{"type":"string"},{"$ref":"#\/definitions\/CommandInputMapSchema"},{"$ref":"#\/definitions\/CommandInputArraySchema"},{"$ref":"#\/definitions\/CommandInputEnumSchema"},{"$ref":"#\/definitions\/CommandInputRecordSchema"}]}}]},"___inputBinding":{"$ref":"#\/definitions\/CommandLineBinding"}},"required":["type"]}},{"$eref":{"type":"object","properties":{"___type":{"type":"string","enum":["array"]},"___items":{"anyOf":[{"type":"string","enum":["null"]},{"type":"string","enum":["boolean"]},{"type":"string","enum":["int"]},{"type":"string","enum":["long"]},{"type":"string","enum":["float"]},{"type":"string","enum":["double"]},{"type":"string","enum":["bytes"]},{"type":"string","enum":["string"]},{"type":"string","enum":["File"]},{"$ref":"#\/definitions\/CommandInputSchema"},{"$ref":"#\/definitions\/CommandInputMapSchema"},{"$ref":"#\/definitions\/CommandInputArraySchema"},{"$ref":"#\/definitions\/CommandInputRecordSchema"},{"$ref":"#\/definitions\/CommandInputEnumSchema"},{"type":"string"},{"type":"array","items":{"anyOf":[{"type":"string","enum":["null"]},{"type":"string","enum":["boolean"]},{"type":"string","enum":["int"]},{"type":"string","enum":["long"]},{"type":"string","enum":["float"]},{"type":"string","enum":["double"]},{"type":"string","enum":["bytes"]},{"type":"string","enum":["string"]},{"type":"string","enum":["File"]},{"$ref":"#\/definitions\/CommandInputSchema"},{"$ref":"#\/definitions\/CommandInputMapSchema"},{"$ref":"#\/definitions\/CommandInputArraySchema"},{"$ref":"#\/definitions\/CommandInputEnumSchema"},{"$ref":"#\/definitions\/CommandInputRecordSchema"},{"type":"string"}]}}]},"___inputBinding":{"$ref":"#\/definitions\/CommandLineBinding"}},"required":["items","type"]}},{"$eref":{"type":"object","properties":{"___fields":{"type":"array","items":{"anyOf":[{"$ref":"#\/definitions\/CommandInputSchema"},{"$ref":"#\/definitions\/CommandInputArraySchema"},{"$ref":"#\/definitions\/CommandInputRecordSchema"},{"$ref":"#\/definitions\/CommandInputEnumSchema"},{"$ref":"#\/definitions\/CommandInputMapSchema"}]}},"___type":{"type":"string","enum":["record"]},"___inputBinding":{"$ref":"#\/definitions\/CommandLineBinding"}},"required":["type","fields"]}},{"$eref":{"type":"object","properties":{"___name":{"type":"string"},"___type":{"type":"string","enum":["enum"]},"___symbols":{"type":"array","items":{"type":"string"}},"___inputBinding":{"$ref":"#\/definitions\/CommandLineBinding"}},"required":["type","symbols","name"]}},{"$eref":{"type":"object","properties":{"___type":{"type":"string","enum":["map"]},"___inputBinding":{"$ref":"#\/definitions\/CommandLineBinding"},"___values":{"type":"string"}},"required":["type","values"]}}]}},"___type":{"type":"string","enum":["record"]},"___inputBinding":{"$eref":{"type":"object","properties":{"___itemSeparator":{"type":["string","null"]},"___loadContents":{"type":"boolean"},"___prefix":{"type":"string"},"___secondaryFiles":{"anyOf":[{"type":"string"},{"$ref":"#\/definitions\/Expression"},{"type":"array","items":{"anyOf":[{"type":"string"},{"$ref":"#\/definitions\/Expression"}]}}]},"___valueFrom":{"anyOf":[{"type":"string"},{"$ref":"#\/definitions\/Expression"}]},"___separate":{"type":"boolean"},"___position":{"type":"number"}}}}},"required":["type","fields"]},"_88Expression":{"type":"object","properties":{"___script":{"type":"string"},"___class":{"type":"string","enum":["Expression"]},"___engine":{"type":"string"}},"required":["engine","script","class"]},"_88CommandInputParameter":{"type":"object","properties":{"___streamable":{"type":"boolean"},"___description":{"type":"string"},"___type":{"anyOf":[{"type":"string","enum":["null"]},{"type":"string","enum":["boolean"]},{"type":"string","enum":["int"]},{"type":"string","enum":["long"]},{"type":"string","enum":["float"]},{"type":"string","enum":["double"]},{"type":"string","enum":["bytes"]},{"type":"string","enum":["string"]},{"type":"string","enum":["File"]},{"$eref":{"type":"object","properties":{"___type":{"anyOf":[{"type":"string","enum":["null"]},{"type":"string","enum":["boolean"]},{"type":"string","enum":["int"]},{"type":"string","enum":["long"]},{"type":"string","enum":["float"]},{"type":"string","enum":["double"]},{"type":"string","enum":["bytes"]},{"type":"string","enum":["string"]},{"type":"string","enum":["File"]},{"$ref":"#\/definitions\/CommandInputSchema"},{"type":"string"},{"$ref":"#\/definitions\/CommandInputMapSchema"},{"$ref":"#\/definitions\/CommandInputArraySchema"},{"$ref":"#\/definitions\/CommandInputRecordSchema"},{"$ref":"#\/definitions\/CommandInputEnumSchema"},{"type":"array","items":{"anyOf":[{"type":"string","enum":["null"]},{"type":"string","enum":["boolean"]},{"type":"string","enum":["int"]},{"type":"string","enum":["long"]},{"type":"string","enum":["float"]},{"type":"string","enum":["double"]},{"type":"string","enum":["bytes"]},{"type":"string","enum":["string"]},{"type":"string","enum":["File"]},{"$ref":"#\/definitions\/CommandInputSchema"},{"type":"string"},{"$ref":"#\/definitions\/CommandInputMapSchema"},{"$ref":"#\/definitions\/CommandInputArraySchema"},{"$ref":"#\/definitions\/CommandInputEnumSchema"},{"$ref":"#\/definitions\/CommandInputRecordSchema"}]}}]},"___inputBinding":{"$ref":"#\/definitions\/CommandLineBinding"}},"required":["type"]}},{"$eref":{"type":"object","properties":{"___type":{"type":"string","enum":["array"]},"___items":{"anyOf":[{"type":"string","enum":["null"]},{"type":"string","enum":["boolean"]},{"type":"string","enum":["int"]},{"type":"string","enum":["long"]},{"type":"string","enum":["float"]},{"type":"string","enum":["double"]},{"type":"string","enum":["bytes"]},{"type":"string","enum":["string"]},{"type":"string","enum":["File"]},{"$ref":"#\/definitions\/CommandInputSchema"},{"$ref":"#\/definitions\/CommandInputMapSchema"},{"$ref":"#\/definitions\/CommandInputArraySchema"},{"$ref":"#\/definitions\/CommandInputRecordSchema"},{"$ref":"#\/definitions\/CommandInputEnumSchema"},{"type":"string"},{"type":"array","items":{"anyOf":[{"type":"string","enum":["null"]},{"type":"string","enum":["boolean"]},{"type":"string","enum":["int"]},{"type":"string","enum":["long"]},{"type":"string","enum":["float"]},{"type":"string","enum":["double"]},{"type":"string","enum":["bytes"]},{"type":"string","enum":["string"]},{"type":"string","enum":["File"]},{"$ref":"#\/definitions\/CommandInputSchema"},{"$ref":"#\/definitions\/CommandInputMapSchema"},{"$ref":"#\/definitions\/CommandInputArraySchema"},{"$ref":"#\/definitions\/CommandInputEnumSchema"},{"$ref":"#\/definitions\/CommandInputRecordSchema"},{"type":"string"}]}}]},"___inputBinding":{"$ref":"#\/definitions\/CommandLineBinding"}},"required":["items","type"]}},{"$eref":{"type":"object","properties":{"___type":{"type":"string","enum":["map"]},"___inputBinding":{"$ref":"#\/definitions\/CommandLineBinding"},"___values":{"type":"string"}},"required":["type","values"]}},{"$eref":{"type":"object","properties":{"___name":{"type":"string"},"___type":{"type":"string","enum":["enum"]},"___symbols":{"type":"array","items":{"type":"string"}},"___inputBinding":{"$ref":"#\/definitions\/CommandLineBinding"}},"required":["type","symbols","name"]}},{"$eref":{"type":"object","properties":{"___fields":{"type":"array","items":{"anyOf":[{"$ref":"#\/definitions\/CommandInputSchema"},{"$ref":"#\/definitions\/CommandInputArraySchema"},{"$ref":"#\/definitions\/CommandInputRecordSchema"},{"$ref":"#\/definitions\/CommandInputEnumSchema"},{"$ref":"#\/definitions\/CommandInputMapSchema"}]}},"___type":{"type":"string","enum":["record"]},"___inputBinding":{"$ref":"#\/definitions\/CommandLineBinding"}},"required":["type","fields"]}},{"type":"string"},{"type":"array","items":{"anyOf":[{"type":"string","enum":["null"]},{"type":"string","enum":["boolean"]},{"type":"string","enum":["int"]},{"type":"string","enum":["long"]},{"type":"string","enum":["float"]},{"type":"string","enum":["double"]},{"type":"string","enum":["bytes"]},{"type":"string","enum":["string"]},{"type":"string","enum":["File"]},{"$eref":{"type":"object","properties":{"___type":{"anyOf":[{"type":"string","enum":["null"]},{"type":"string","enum":["boolean"]},{"type":"string","enum":["int"]},{"type":"string","enum":["long"]},{"type":"string","enum":["float"]},{"type":"string","enum":["double"]},{"type":"string","enum":["bytes"]},{"type":"string","enum":["string"]},{"type":"string","enum":["File"]},{"$ref":"#\/definitions\/CommandInputSchema"},{"type":"string"},{"$ref":"#\/definitions\/CommandInputMapSchema"},{"$ref":"#\/definitions\/CommandInputArraySchema"},{"$ref":"#\/definitions\/CommandInputRecordSchema"},{"$ref":"#\/definitions\/CommandInputEnumSchema"},{"type":"array","items":{"anyOf":[{"type":"string","enum":["null"]},{"type":"string","enum":["boolean"]},{"type":"string","enum":["int"]},{"type":"string","enum":["long"]},{"type":"string","enum":["float"]},{"type":"string","enum":["double"]},{"type":"string","enum":["bytes"]},{"type":"string","enum":["string"]},{"type":"string","enum":["File"]},{"$ref":"#\/definitions\/CommandInputSchema"},{"type":"string"},{"$ref":"#\/definitions\/CommandInputMapSchema"},{"$ref":"#\/definitions\/CommandInputArraySchema"},{"$ref":"#\/definitions\/CommandInputEnumSchema"},{"$ref":"#\/definitions\/CommandInputRecordSchema"}]}}]},"___inputBinding":{"$ref":"#\/definitions\/CommandLineBinding"}},"required":["type"]}},{"$eref":{"type":"object","properties":{"___type":{"type":"string","enum":["array"]},"___items":{"anyOf":[{"type":"string","enum":["null"]},{"type":"string","enum":["boolean"]},{"type":"string","enum":["int"]},{"type":"string","enum":["long"]},{"type":"string","enum":["float"]},{"type":"string","enum":["double"]},{"type":"string","enum":["bytes"]},{"type":"string","enum":["string"]},{"type":"string","enum":["File"]},{"$ref":"#\/definitions\/CommandInputSchema"},{"$ref":"#\/definitions\/CommandInputMapSchema"},{"$ref":"#\/definitions\/CommandInputArraySchema"},{"$ref":"#\/definitions\/CommandInputRecordSchema"},{"$ref":"#\/definitions\/CommandInputEnumSchema"},{"type":"string"},{"type":"array","items":{"anyOf":[{"type":"string","enum":["null"]},{"type":"string","enum":["boolean"]},{"type":"string","enum":["int"]},{"type":"string","enum":["long"]},{"type":"string","enum":["float"]},{"type":"string","enum":["double"]},{"type":"string","enum":["bytes"]},{"type":"string","enum":["string"]},{"type":"string","enum":["File"]},{"$ref":"#\/definitions\/CommandInputSchema"},{"$ref":"#\/definitions\/CommandInputMapSchema"},{"$ref":"#\/definitions\/CommandInputArraySchema"},{"$ref":"#\/definitions\/CommandInputEnumSchema"},{"$ref":"#\/definitions\/CommandInputRecordSchema"},{"type":"string"}]}}]},"___inputBinding":{"$ref":"#\/definitions\/CommandLineBinding"}},"required":["items","type"]}},{"$eref":{"type":"object","properties":{"___type":{"type":"string","enum":["map"]},"___inputBinding":{"$ref":"#\/definitions\/CommandLineBinding"},"___values":{"type":"string"}},"required":["type","values"]}},{"$eref":{"type":"object","properties":{"___name":{"type":"string"},"___type":{"type":"string","enum":["enum"]},"___symbols":{"type":"array","items":{"type":"string"}},"___inputBinding":{"$ref":"#\/definitions\/CommandLineBinding"}},"required":["type","symbols","name"]}},{"$eref":{"type":"object","properties":{"___fields":{"type":"array","items":{"anyOf":[{"$ref":"#\/definitions\/CommandInputSchema"},{"$ref":"#\/definitions\/CommandInputArraySchema"},{"$ref":"#\/definitions\/CommandInputRecordSchema"},{"$ref":"#\/definitions\/CommandInputEnumSchema"},{"$ref":"#\/definitions\/CommandInputMapSchema"}]}},"___type":{"type":"string","enum":["record"]},"___inputBinding":{"$ref":"#\/definitions\/CommandLineBinding"}},"required":["type","fields"]}},{"type":"string"}]}}]},"___inputBinding":{"$eref":{"type":"object","properties":{"___itemSeparator":{"type":["string","null"]},"___loadContents":{"type":"boolean"},"___prefix":{"type":"string"},"___secondaryFiles":{"anyOf":[{"type":"string"},{"$ref":"#\/definitions\/Expression"},{"type":"array","items":{"anyOf":[{"type":"string"},{"$ref":"#\/definitions\/Expression"}]}}]},"___valueFrom":{"anyOf":[{"type":"string"},{"$ref":"#\/definitions\/Expression"}]},"___separate":{"type":"boolean"},"___position":{"type":"number"}}}},"___default":{},"___sbg:category":{"type":"string"},"___id":{"type":"string"},"___label":{"type":"string"},"___sbg:fileTypes":{"type":"string"}},"required":["id"]},"_88CommandOutputBinding":{"type":"object","properties":{"___glob":{"anyOf":[{"type":"string"},{"$eref":{"type":"object","properties":{"___script":{"type":"string"},"___class":{"type":"string","enum":["Expression"]},"___engine":{"type":"string"}},"required":["engine","script","class"]}},{"type":"array","items":{"type":"string"}}]},"___loadContents":{"type":"boolean"},"___outputEval":{"$eref":{"type":"object","properties":{"___script":{"type":"string"},"___class":{"type":"string","enum":["Expression"]},"___engine":{"type":"string"}},"required":["engine","script","class"]}},"___secondaryFiles":{"anyOf":[{"type":"string"},{"$eref":{"type":"object","properties":{"___script":{"type":"string"},"___class":{"type":"string","enum":["Expression"]},"___engine":{"type":"string"}},"required":["engine","script","class"]}},{"type":"array","items":{"anyOf":[{"type":"string"},{"$eref":{"type":"object","properties":{"___script":{"type":"string"},"___class":{"type":"string","enum":["Expression"]},"___engine":{"type":"string"}},"required":["engine","script","class"]}}]}}]},"___sbg:metadata":{"additionalProperties":{"anyOf":[{"type":"string"},{"$eref":{"type":"object","properties":{"___script":{"type":"string"},"___class":{"type":"string","enum":["Expression"]},"___engine":{"type":"string"}},"required":["engine","script","class"]}}]},"type":"object"},"___sbg:inheritMetadataFrom":{"type":"string"}}},"_88CommandOutputArraySchema":{"type":"object","properties":{"___type":{"type":"string","enum":["array"]},"___outputBinding":{"$eref":{"type":"object","properties":{"___glob":{"anyOf":[{"type":"string"},{"$ref":"#\/definitions\/Expression"},{"type":"array","items":{"type":"string"}}]},"___loadContents":{"type":"boolean"},"___outputEval":{"$ref":"#\/definitions\/Expression"},"___secondaryFiles":{"anyOf":[{"type":"string"},{"$ref":"#\/definitions\/Expression"},{"type":"array","items":{"anyOf":[{"type":"string"},{"$ref":"#\/definitions\/Expression"}]}}]},"___sbg:metadata":{"additionalProperties":{"anyOf":[{"type":"string"},{"$ref":"#\/definitions\/Expression"}]},"type":"object"},"___sbg:inheritMetadataFrom":{"type":"string"}}}},"___items":{"anyOf":[{"type":"string","enum":["null"]},{"type":"string","enum":["boolean"]},{"type":"string","enum":["int"]},{"type":"string","enum":["long"]},{"type":"string","enum":["float"]},{"type":"string","enum":["double"]},{"type":"string","enum":["bytes"]},{"type":"string","enum":["string"]},{"type":"string","enum":["File"]},{"$eref":{"type":"object","properties":{"___type":{"anyOf":[{"type":"string","enum":["null"]},{"type":"string","enum":["boolean"]},{"type":"string","enum":["int"]},{"type":"string","enum":["long"]},{"type":"string","enum":["float"]},{"type":"string","enum":["double"]},{"type":"string","enum":["bytes"]},{"type":"string","enum":["string"]},{"type":"string","enum":["File"]},{"$ref":"#\/definitions\/CommandOutputSchema"},{"type":"string"},{"$ref":"#\/definitions\/CommandOutputMapSchema"},{"$ref":"#\/definitions\/CommandOutputArraySchema"},{"$ref":"#\/definitions\/CommandOutputRecordSchema"},{"$ref":"#\/definitions\/CommandOutputEnumSchema"},{"type":"array","items":{"anyOf":[{"type":"string","enum":["null"]},{"type":"string","enum":["boolean"]},{"type":"string","enum":["int"]},{"type":"string","enum":["long"]},{"type":"string","enum":["float"]},{"type":"string","enum":["double"]},{"type":"string","enum":["bytes"]},{"type":"string","enum":["string"]},{"type":"string","enum":["File"]},{"$ref":"#\/definitions\/CommandOutputSchema"},{"type":"string"},{"$ref":"#\/definitions\/CommandOutputMapSchema"},{"$ref":"#\/definitions\/CommandOutputArraySchema"},{"$ref":"#\/definitions\/CommandOutputEnumSchema"},{"$ref":"#\/definitions\/CommandOutputRecordSchema"}]}}]},"___outputBinding":{"$ref":"#\/definitions\/CommandOutputBinding"}},"required":["type"]}},{"$eref":{"type":"object","properties":{"___type":{"type":"string","enum":["map"]},"___outputBinding":{"$ref":"#\/definitions\/CommandOutputBinding"},"___values":{"type":"string"}},"required":["type","values"]}},{"$eref":{"type":"object","properties":{"___type":{"type":"string","enum":["array"]},"___outputBinding":{"$ref":"#\/definitions\/CommandOutputBinding"},"___items":{"anyOf":[{"type":"string","enum":["null"]},{"type":"string","enum":["boolean"]},{"type":"string","enum":["int"]},{"type":"string","enum":["long"]},{"type":"string","enum":["float"]},{"type":"string","enum":["double"]},{"type":"string","enum":["bytes"]},{"type":"string","enum":["string"]},{"type":"string","enum":["File"]},{"$ref":"#\/definitions\/CommandOutputSchema"},{"$ref":"#\/definitions\/CommandOutputMapSchema"},{"$ref":"#\/definitions\/CommandOutputArraySchema"},{"$ref":"#\/definitions\/CommandOutputRecordSchema"},{"$ref":"#\/definitions\/CommandOutputEnumSchema"},{"type":"string"},{"type":"array","items":{"anyOf":[{"type":"string","enum":["null"]},{"type":"string","enum":["boolean"]},{"type":"string","enum":["int"]},{"type":"string","enum":["long"]},{"type":"string","enum":["float"]},{"type":"string","enum":["double"]},{"type":"string","enum":["bytes"]},{"type":"string","enum":["string"]},{"type":"string","enum":["File"]},{"$ref":"#\/definitions\/CommandOutputSchema"},{"$ref":"#\/definitions\/CommandOutputMapSchema"},{"$ref":"#\/definitions\/CommandOutputArraySchema"},{"$ref":"#\/definitions\/CommandOutputEnumSchema"},{"$ref":"#\/definitions\/CommandOutputRecordSchema"},{"type":"string"}]}}]}},"required":["items","type"]}},{"$eref":{"type":"object","properties":{"___fields":{"type":"array","items":{"anyOf":[{"$ref":"#\/definitions\/CommandOutputSchema"},{"$ref":"#\/definitions\/CommandOutputArraySchema"},{"$ref":"#\/definitions\/CommandOutputRecordSchema"},{"$ref":"#\/definitions\/CommandOutputEnumSchema"},{"$ref":"#\/definitions\/CommandOutputMapSchema"}]}},"___type":{"type":"string","enum":["record"]},"___outputBinding":{"$ref":"#\/definitions\/CommandOutputBinding"}},"required":["type","fields"]}},{"$eref":{"type":"object","properties":{"___type":{"type":"string","enum":["enum"]},"___outputBinding":{"$ref":"#\/definitions\/CommandOutputBinding"},"___symbols":{"type":"array","items":{"type":"string"}}},"required":["type","symbols"]}},{"type":"string"},{"type":"array","items":{"anyOf":[{"type":"string","enum":["null"]},{"type":"string","enum":["boolean"]},{"type":"string","enum":["int"]},{"type":"string","enum":["long"]},{"type":"string","enum":["float"]},{"type":"string","enum":["double"]},{"type":"string","enum":["bytes"]},{"type":"string","enum":["string"]},{"type":"string","enum":["File"]},{"$eref":{"type":"object","properties":{"___type":{"anyOf":[{"type":"string","enum":["null"]},{"type":"string","enum":["boolean"]},{"type":"string","enum":["int"]},{"type":"string","enum":["long"]},{"type":"string","enum":["float"]},{"type":"string","enum":["double"]},{"type":"string","enum":["bytes"]},{"type":"string","enum":["string"]},{"type":"string","enum":["File"]},{"$ref":"#\/definitions\/CommandOutputSchema"},{"type":"string"},{"$ref":"#\/definitions\/CommandOutputMapSchema"},{"$ref":"#\/definitions\/CommandOutputArraySchema"},{"$ref":"#\/definitions\/CommandOutputRecordSchema"},{"$ref":"#\/definitions\/CommandOutputEnumSchema"},{"type":"array","items":{"anyOf":[{"type":"string","enum":["null"]},{"type":"string","enum":["boolean"]},{"type":"string","enum":["int"]},{"type":"string","enum":["long"]},{"type":"string","enum":["float"]},{"type":"string","enum":["double"]},{"type":"string","enum":["bytes"]},{"type":"string","enum":["string"]},{"type":"string","enum":["File"]},{"$ref":"#\/definitions\/CommandOutputSchema"},{"type":"string"},{"$ref":"#\/definitions\/CommandOutputMapSchema"},{"$ref":"#\/definitions\/CommandOutputArraySchema"},{"$ref":"#\/definitions\/CommandOutputEnumSchema"},{"$ref":"#\/definitions\/CommandOutputRecordSchema"}]}}]},"___outputBinding":{"$ref":"#\/definitions\/CommandOutputBinding"}},"required":["type"]}},{"$eref":{"type":"object","properties":{"___type":{"type":"string","enum":["map"]},"___outputBinding":{"$ref":"#\/definitions\/CommandOutputBinding"},"___values":{"type":"string"}},"required":["type","values"]}},{"$eref":{"type":"object","properties":{"___type":{"type":"string","enum":["array"]},"___outputBinding":{"$ref":"#\/definitions\/CommandOutputBinding"},"___items":{"anyOf":[{"type":"string","enum":["null"]},{"type":"string","enum":["boolean"]},{"type":"string","enum":["int"]},{"type":"string","enum":["long"]},{"type":"string","enum":["float"]},{"type":"string","enum":["double"]},{"type":"string","enum":["bytes"]},{"type":"string","enum":["string"]},{"type":"string","enum":["File"]},{"$ref":"#\/definitions\/CommandOutputSchema"},{"$ref":"#\/definitions\/CommandOutputMapSchema"},{"$ref":"#\/definitions\/CommandOutputArraySchema"},{"$ref":"#\/definitions\/CommandOutputRecordSchema"},{"$ref":"#\/definitions\/CommandOutputEnumSchema"},{"type":"string"},{"type":"array","items":{"anyOf":[{"type":"string","enum":["null"]},{"type":"string","enum":["boolean"]},{"type":"string","enum":["int"]},{"type":"string","enum":["long"]},{"type":"string","enum":["float"]},{"type":"string","enum":["double"]},{"type":"string","enum":["bytes"]},{"type":"string","enum":["string"]},{"type":"string","enum":["File"]},{"$ref":"#\/definitions\/CommandOutputSchema"},{"$ref":"#\/definitions\/CommandOutputMapSchema"},{"$ref":"#\/definitions\/CommandOutputArraySchema"},{"$ref":"#\/definitions\/CommandOutputEnumSchema"},{"$ref":"#\/definitions\/CommandOutputRecordSchema"},{"type":"string"}]}}]}},"required":["items","type"]}},{"$eref":{"type":"object","properties":{"___type":{"type":"string","enum":["enum"]},"___outputBinding":{"$ref":"#\/definitions\/CommandOutputBinding"},"___symbols":{"type":"array","items":{"type":"string"}}},"required":["type","symbols"]}},{"$eref":{"type":"object","properties":{"___fields":{"type":"array","items":{"anyOf":[{"$ref":"#\/definitions\/CommandOutputSchema"},{"$ref":"#\/definitions\/CommandOutputArraySchema"},{"$ref":"#\/definitions\/CommandOutputRecordSchema"},{"$ref":"#\/definitions\/CommandOutputEnumSchema"},{"$ref":"#\/definitions\/CommandOutputMapSchema"}]}},"___type":{"type":"string","enum":["record"]},"___outputBinding":{"$ref":"#\/definitions\/CommandOutputBinding"}},"required":["type","fields"]}},{"type":"string"}]}}]}},"required":["items","type"]},"_88SchemaDefRequirement":{"type":"object","properties":{}},"_88CommandOutputEnumSchema":{"type":"object","properties":{"___type":{"type":"string","enum":["enum"]},"___outputBinding":{"$eref":{"type":"object","properties":{"___glob":{"anyOf":[{"type":"string"},{"$ref":"#\/definitions\/Expression"},{"type":"array","items":{"type":"string"}}]},"___loadContents":{"type":"boolean"},"___outputEval":{"$ref":"#\/definitions\/Expression"},"___secondaryFiles":{"anyOf":[{"type":"string"},{"$ref":"#\/definitions\/Expression"},{"type":"array","items":{"anyOf":[{"type":"string"},{"$ref":"#\/definitions\/Expression"}]}}]},"___sbg:metadata":{"additionalProperties":{"anyOf":[{"type":"string"},{"$ref":"#\/definitions\/Expression"}]},"type":"object"},"___sbg:inheritMetadataFrom":{"type":"string"}}}},"___symbols":{"type":"array","items":{"type":"string"}}},"required":["type","symbols"]},"_88CommandOutputMapSchema":{"type":"object","properties":{"___type":{"type":"string","enum":["map"]},"___outputBinding":{"$eref":{"type":"object","properties":{"___glob":{"anyOf":[{"type":"string"},{"$ref":"#\/definitions\/Expression"},{"type":"array","items":{"type":"string"}}]},"___loadContents":{"type":"boolean"},"___outputEval":{"$ref":"#\/definitions\/Expression"},"___secondaryFiles":{"anyOf":[{"type":"string"},{"$ref":"#\/definitions\/Expression"},{"type":"array","items":{"anyOf":[{"type":"string"},{"$ref":"#\/definitions\/Expression"}]}}]},"___sbg:metadata":{"additionalProperties":{"anyOf":[{"type":"string"},{"$ref":"#\/definitions\/Expression"}]},"type":"object"},"___sbg:inheritMetadataFrom":{"type":"string"}}}},"___values":{"type":"string"}},"required":["type","values"]},"_88CommandOutputRecordSchema":{"type":"object","properties":{"___fields":{"type":"array","items":{"anyOf":[{"$eref":{"type":"object","properties":{"___type":{"anyOf":[{"type":"string","enum":["null"]},{"type":"string","enum":["boolean"]},{"type":"string","enum":["int"]},{"type":"string","enum":["long"]},{"type":"string","enum":["float"]},{"type":"string","enum":["double"]},{"type":"string","enum":["bytes"]},{"type":"string","enum":["string"]},{"type":"string","enum":["File"]},{"$ref":"#\/definitions\/CommandOutputSchema"},{"type":"string"},{"$ref":"#\/definitions\/CommandOutputMapSchema"},{"$ref":"#\/definitions\/CommandOutputArraySchema"},{"$ref":"#\/definitions\/CommandOutputRecordSchema"},{"$ref":"#\/definitions\/CommandOutputEnumSchema"},{"type":"array","items":{"anyOf":[{"type":"string","enum":["null"]},{"type":"string","enum":["boolean"]},{"type":"string","enum":["int"]},{"type":"string","enum":["long"]},{"type":"string","enum":["float"]},{"type":"string","enum":["double"]},{"type":"string","enum":["bytes"]},{"type":"string","enum":["string"]},{"type":"string","enum":["File"]},{"$ref":"#\/definitions\/CommandOutputSchema"},{"type":"string"},{"$ref":"#\/definitions\/CommandOutputMapSchema"},{"$ref":"#\/definitions\/CommandOutputArraySchema"},{"$ref":"#\/definitions\/CommandOutputEnumSchema"},{"$ref":"#\/definitions\/CommandOutputRecordSchema"}]}}]},"___outputBinding":{"$ref":"#\/definitions\/CommandOutputBinding"}},"required":["type"]}},{"$eref":{"type":"object","properties":{"___type":{"type":"string","enum":["array"]},"___outputBinding":{"$ref":"#\/definitions\/CommandOutputBinding"},"___items":{"anyOf":[{"type":"string","enum":["null"]},{"type":"string","enum":["boolean"]},{"type":"string","enum":["int"]},{"type":"string","enum":["long"]},{"type":"string","enum":["float"]},{"type":"string","enum":["double"]},{"type":"string","enum":["bytes"]},{"type":"string","enum":["string"]},{"type":"string","enum":["File"]},{"$ref":"#\/definitions\/CommandOutputSchema"},{"$ref":"#\/definitions\/CommandOutputMapSchema"},{"$ref":"#\/definitions\/CommandOutputArraySchema"},{"$ref":"#\/definitions\/CommandOutputRecordSchema"},{"$ref":"#\/definitions\/CommandOutputEnumSchema"},{"type":"string"},{"type":"array","items":{"anyOf":[{"type":"string","enum":["null"]},{"type":"string","enum":["boolean"]},{"type":"string","enum":["int"]},{"type":"string","enum":["long"]},{"type":"string","enum":["float"]},{"type":"string","enum":["double"]},{"type":"string","enum":["bytes"]},{"type":"string","enum":["string"]},{"type":"string","enum":["File"]},{"$ref":"#\/definitions\/CommandOutputSchema"},{"$ref":"#\/definitions\/CommandOutputMapSchema"},{"$ref":"#\/definitions\/CommandOutputArraySchema"},{"$ref":"#\/definitions\/CommandOutputEnumSchema"},{"$ref":"#\/definitions\/CommandOutputRecordSchema"},{"type":"string"}]}}]}},"required":["items","type"]}},{"$eref":{"type":"object","properties":{"___fields":{"type":"array","items":{"anyOf":[{"$ref":"#\/definitions\/CommandOutputSchema"},{"$ref":"#\/definitions\/CommandOutputArraySchema"},{"$ref":"#\/definitions\/CommandOutputRecordSchema"},{"$ref":"#\/definitions\/CommandOutputEnumSchema"},{"$ref":"#\/definitions\/CommandOutputMapSchema"}]}},"___type":{"type":"string","enum":["record"]},"___outputBinding":{"$ref":"#\/definitions\/CommandOutputBinding"}},"required":["type","fields"]}},{"$eref":{"type":"object","properties":{"___type":{"type":"string","enum":["enum"]},"___outputBinding":{"$ref":"#\/definitions\/CommandOutputBinding"},"___symbols":{"type":"array","items":{"type":"string"}}},"required":["type","symbols"]}},{"$eref":{"type":"object","properties":{"___type":{"type":"string","enum":["map"]},"___outputBinding":{"$ref":"#\/definitions\/CommandOutputBinding"},"___values":{"type":"string"}},"required":["type","values"]}}]}},"___type":{"type":"string","enum":["record"]},"___outputBinding":{"$eref":{"type":"object","properties":{"___glob":{"anyOf":[{"type":"string"},{"$ref":"#\/definitions\/Expression"},{"type":"array","items":{"type":"string"}}]},"___loadContents":{"type":"boolean"},"___outputEval":{"$ref":"#\/definitions\/Expression"},"___secondaryFiles":{"anyOf":[{"type":"string"},{"$ref":"#\/definitions\/Expression"},{"type":"array","items":{"anyOf":[{"type":"string"},{"$ref":"#\/definitions\/Expression"}]}}]},"___sbg:metadata":{"additionalProperties":{"anyOf":[{"type":"string"},{"$ref":"#\/definitions\/Expression"}]},"type":"object"},"___sbg:inheritMetadataFrom":{"type":"string"}}}}},"required":["type","fields"]},"_88ScatterFeatureRequirement":{"type":"object","properties":{}},"_88CommandOutputParameter":{"type":"object","properties":{"___streamable":{"type":"boolean"},"___description":{"type":"string"},"___type":{"anyOf":[{"type":"string","enum":["null"]},{"type":"string","enum":["boolean"]},{"type":"string","enum":["int"]},{"type":"string","enum":["long"]},{"type":"string","enum":["float"]},{"type":"string","enum":["double"]},{"type":"string","enum":["bytes"]},{"type":"string","enum":["string"]},{"type":"string","enum":["File"]},{"$eref":{"type":"object","properties":{"___type":{"anyOf":[{"type":"string","enum":["null"]},{"type":"string","enum":["boolean"]},{"type":"string","enum":["int"]},{"type":"string","enum":["long"]},{"type":"string","enum":["float"]},{"type":"string","enum":["double"]},{"type":"string","enum":["bytes"]},{"type":"string","enum":["string"]},{"type":"string","enum":["File"]},{"$ref":"#\/definitions\/CommandOutputSchema"},{"type":"string"},{"$ref":"#\/definitions\/CommandOutputMapSchema"},{"$ref":"#\/definitions\/CommandOutputArraySchema"},{"$ref":"#\/definitions\/CommandOutputRecordSchema"},{"$ref":"#\/definitions\/CommandOutputEnumSchema"},{"type":"array","items":{"anyOf":[{"type":"string","enum":["null"]},{"type":"string","enum":["boolean"]},{"type":"string","enum":["int"]},{"type":"string","enum":["long"]},{"type":"string","enum":["float"]},{"type":"string","enum":["double"]},{"type":"string","enum":["bytes"]},{"type":"string","enum":["string"]},{"type":"string","enum":["File"]},{"$ref":"#\/definitions\/CommandOutputSchema"},{"type":"string"},{"$ref":"#\/definitions\/CommandOutputMapSchema"},{"$ref":"#\/definitions\/CommandOutputArraySchema"},{"$ref":"#\/definitions\/CommandOutputEnumSchema"},{"$ref":"#\/definitions\/CommandOutputRecordSchema"}]}}]},"___outputBinding":{"$ref":"#\/definitions\/CommandOutputBinding"}},"required":["type"]}},{"type":"string"},{"type":"array","items":{"anyOf":[{"type":"string","enum":["null"]},{"type":"string","enum":["boolean"]},{"type":"string","enum":["int"]},{"type":"string","enum":["long"]},{"type":"string","enum":["float"]},{"type":"string","enum":["double"]},{"type":"string","enum":["bytes"]},{"type":"string","enum":["string"]},{"type":"string","enum":["File"]},{"$eref":{"type":"object","properties":{"___type":{"anyOf":[{"type":"string","enum":["null"]},{"type":"string","enum":["boolean"]},{"type":"string","enum":["int"]},{"type":"string","enum":["long"]},{"type":"string","enum":["float"]},{"type":"string","enum":["double"]},{"type":"string","enum":["bytes"]},{"type":"string","enum":["string"]},{"type":"string","enum":["File"]},{"$ref":"#\/definitions\/CommandOutputSchema"},{"type":"string"},{"$ref":"#\/definitions\/CommandOutputMapSchema"},{"$ref":"#\/definitions\/CommandOutputArraySchema"},{"$ref":"#\/definitions\/CommandOutputRecordSchema"},{"$ref":"#\/definitions\/CommandOutputEnumSchema"},{"type":"array","items":{"anyOf":[{"type":"string","enum":["null"]},{"type":"string","enum":["boolean"]},{"type":"string","enum":["int"]},{"type":"string","enum":["long"]},{"type":"string","enum":["float"]},{"type":"string","enum":["double"]},{"type":"string","enum":["bytes"]},{"type":"string","enum":["string"]},{"type":"string","enum":["File"]},{"$ref":"#\/definitions\/CommandOutputSchema"},{"type":"string"},{"$ref":"#\/definitions\/CommandOutputMapSchema"},{"$ref":"#\/definitions\/CommandOutputArraySchema"},{"$ref":"#\/definitions\/CommandOutputEnumSchema"},{"$ref":"#\/definitions\/CommandOutputRecordSchema"}]}}]},"___outputBinding":{"$ref":"#\/definitions\/CommandOutputBinding"}},"required":["type"]}},{"type":"string"}]}}]},"___outputBinding":{"$eref":{"type":"object","properties":{"___glob":{"anyOf":[{"type":"string"},{"$ref":"#\/definitions\/Expression"},{"type":"array","items":{"type":"string"}}]},"___loadContents":{"type":"boolean"},"___outputEval":{"$ref":"#\/definitions\/Expression"},"___secondaryFiles":{"anyOf":[{"type":"string"},{"$ref":"#\/definitions\/Expression"},{"type":"array","items":{"anyOf":[{"type":"string"},{"$ref":"#\/definitions\/Expression"}]}}]},"___sbg:metadata":{"additionalProperties":{"anyOf":[{"type":"string"},{"$ref":"#\/definitions\/Expression"}]},"type":"object"},"___sbg:inheritMetadataFrom":{"type":"string"}}}},"___default":{},"___id":{"type":"string"},"___label":{"type":"string"},"___sbg:fileTypes":{"type":"string"}},"required":["id"]},"_88CreateFileRequirement":{"type":"object","properties":{"___fileDef":{"type":"array","items":{"$eref":{"type":"object","properties":{"___fileContent":{"anyOf":[{"type":"string"},{"$ref":"#\/definitions\/Expression"}]},"___filename":{"anyOf":[{"type":"string"},{"$ref":"#\/definitions\/Expression"}]}},"required":["filename","fileContent"]}}},"___class":{"type":"string","enum":["CreateFileRequirement"]}},"required":["class","fileDef"]},"_88EnvVarRequirement":{"type":"object","properties":{}},"_88CommandInputArraySchema":{"type":"object","properties":{"___type":{"type":"string","enum":["array"]},"___items":{"anyOf":[{"type":"string","enum":["null"]},{"type":"string","enum":["boolean"]},{"type":"string","enum":["int"]},{"type":"string","enum":["long"]},{"type":"string","enum":["float"]},{"type":"string","enum":["double"]},{"type":"string","enum":["bytes"]},{"type":"string","enum":["string"]},{"type":"string","enum":["File"]},{"$eref":{"type":"object","properties":{"___type":{"anyOf":[{"type":"string","enum":["null"]},{"type":"string","enum":["boolean"]},{"type":"string","enum":["int"]},{"type":"string","enum":["long"]},{"type":"string","enum":["float"]},{"type":"string","enum":["double"]},{"type":"string","enum":["bytes"]},{"type":"string","enum":["string"]},{"type":"string","enum":["File"]},{"$ref":"#\/definitions\/CommandInputSchema"},{"type":"string"},{"$ref":"#\/definitions\/CommandInputMapSchema"},{"$ref":"#\/definitions\/CommandInputArraySchema"},{"$ref":"#\/definitions\/CommandInputRecordSchema"},{"$ref":"#\/definitions\/CommandInputEnumSchema"},{"type":"array","items":{"anyOf":[{"type":"string","enum":["null"]},{"type":"string","enum":["boolean"]},{"type":"string","enum":["int"]},{"type":"string","enum":["long"]},{"type":"string","enum":["float"]},{"type":"string","enum":["double"]},{"type":"string","enum":["bytes"]},{"type":"string","enum":["string"]},{"type":"string","enum":["File"]},{"$ref":"#\/definitions\/CommandInputSchema"},{"type":"string"},{"$ref":"#\/definitions\/CommandInputMapSchema"},{"$ref":"#\/definitions\/CommandInputArraySchema"},{"$ref":"#\/definitions\/CommandInputEnumSchema"},{"$ref":"#\/definitions\/CommandInputRecordSchema"}]}}]},"___inputBinding":{"$ref":"#\/definitions\/CommandLineBinding"}},"required":["type"]}},{"$eref":{"type":"object","properties":{"___type":{"type":"string","enum":["map"]},"___inputBinding":{"$ref":"#\/definitions\/CommandLineBinding"},"___values":{"type":"string"}},"required":["type","values"]}},{"$eref":{"type":"object","properties":{"___type":{"type":"string","enum":["array"]},"___items":{"anyOf":[{"type":"string","enum":["null"]},{"type":"string","enum":["boolean"]},{"type":"string","enum":["int"]},{"type":"string","enum":["long"]},{"type":"string","enum":["float"]},{"type":"string","enum":["double"]},{"type":"string","enum":["bytes"]},{"type":"string","enum":["string"]},{"type":"string","enum":["File"]},{"$ref":"#\/definitions\/CommandInputSchema"},{"$ref":"#\/definitions\/CommandInputMapSchema"},{"$ref":"#\/definitions\/CommandInputArraySchema"},{"$ref":"#\/definitions\/CommandInputRecordSchema"},{"$ref":"#\/definitions\/CommandInputEnumSchema"},{"type":"string"},{"type":"array","items":{"anyOf":[{"type":"string","enum":["null"]},{"type":"string","enum":["boolean"]},{"type":"string","enum":["int"]},{"type":"string","enum":["long"]},{"type":"string","enum":["float"]},{"type":"string","enum":["double"]},{"type":"string","enum":["bytes"]},{"type":"string","enum":["string"]},{"type":"string","enum":["File"]},{"$ref":"#\/definitions\/CommandInputSchema"},{"$ref":"#\/definitions\/CommandInputMapSchema"},{"$ref":"#\/definitions\/CommandInputArraySchema"},{"$ref":"#\/definitions\/CommandInputEnumSchema"},{"$ref":"#\/definitions\/CommandInputRecordSchema"},{"type":"string"}]}}]},"___inputBinding":{"$ref":"#\/definitions\/CommandLineBinding"}},"required":["items","type"]}},{"$eref":{"type":"object","properties":{"___fields":{"type":"array","items":{"anyOf":[{"$ref":"#\/definitions\/CommandInputSchema"},{"$ref":"#\/definitions\/CommandInputArraySchema"},{"$ref":"#\/definitions\/CommandInputRecordSchema"},{"$ref":"#\/definitions\/CommandInputEnumSchema"},{"$ref":"#\/definitions\/CommandInputMapSchema"}]}},"___type":{"type":"string","enum":["record"]},"___inputBinding":{"$ref":"#\/definitions\/CommandLineBinding"}},"required":["type","fields"]}},{"$eref":{"type":"object","properties":{"___name":{"type":"string"},"___type":{"type":"string","enum":["enum"]},"___symbols":{"type":"array","items":{"type":"string"}},"___inputBinding":{"$ref":"#\/definitions\/CommandLineBinding"}},"required":["type","symbols","name"]}},{"type":"string"},{"type":"array","items":{"anyOf":[{"type":"string","enum":["null"]},{"type":"string","enum":["boolean"]},{"type":"string","enum":["int"]},{"type":"string","enum":["long"]},{"type":"string","enum":["float"]},{"type":"string","enum":["double"]},{"type":"string","enum":["bytes"]},{"type":"string","enum":["string"]},{"type":"string","enum":["File"]},{"$eref":{"type":"object","properties":{"___type":{"anyOf":[{"type":"string","enum":["null"]},{"type":"string","enum":["boolean"]},{"type":"string","enum":["int"]},{"type":"string","enum":["long"]},{"type":"string","enum":["float"]},{"type":"string","enum":["double"]},{"type":"string","enum":["bytes"]},{"type":"string","enum":["string"]},{"type":"string","enum":["File"]},{"$ref":"#\/definitions\/CommandInputSchema"},{"type":"string"},{"$ref":"#\/definitions\/CommandInputMapSchema"},{"$ref":"#\/definitions\/CommandInputArraySchema"},{"$ref":"#\/definitions\/CommandInputRecordSchema"},{"$ref":"#\/definitions\/CommandInputEnumSchema"},{"type":"array","items":{"anyOf":[{"type":"string","enum":["null"]},{"type":"string","enum":["boolean"]},{"type":"string","enum":["int"]},{"type":"string","enum":["long"]},{"type":"string","enum":["float"]},{"type":"string","enum":["double"]},{"type":"string","enum":["bytes"]},{"type":"string","enum":["string"]},{"type":"string","enum":["File"]},{"$ref":"#\/definitions\/CommandInputSchema"},{"type":"string"},{"$ref":"#\/definitions\/CommandInputMapSchema"},{"$ref":"#\/definitions\/CommandInputArraySchema"},{"$ref":"#\/definitions\/CommandInputEnumSchema"},{"$ref":"#\/definitions\/CommandInputRecordSchema"}]}}]},"___inputBinding":{"$ref":"#\/definitions\/CommandLineBinding"}},"required":["type"]}},{"$eref":{"type":"object","properties":{"___type":{"type":"string","enum":["map"]},"___inputBinding":{"$ref":"#\/definitions\/CommandLineBinding"},"___values":{"type":"string"}},"required":["type","values"]}},{"$eref":{"type":"object","properties":{"___type":{"type":"string","enum":["array"]},"___items":{"anyOf":[{"type":"string","enum":["null"]},{"type":"string","enum":["boolean"]},{"type":"string","enum":["int"]},{"type":"string","enum":["long"]},{"type":"string","enum":["float"]},{"type":"string","enum":["double"]},{"type":"string","enum":["bytes"]},{"type":"string","enum":["string"]},{"type":"string","enum":["File"]},{"$ref":"#\/definitions\/CommandInputSchema"},{"$ref":"#\/definitions\/CommandInputMapSchema"},{"$ref":"#\/definitions\/CommandInputArraySchema"},{"$ref":"#\/definitions\/CommandInputRecordSchema"},{"$ref":"#\/definitions\/CommandInputEnumSchema"},{"type":"string"},{"type":"array","items":{"anyOf":[{"type":"string","enum":["null"]},{"type":"string","enum":["boolean"]},{"type":"string","enum":["int"]},{"type":"string","enum":["long"]},{"type":"string","enum":["float"]},{"type":"string","enum":["double"]},{"type":"string","enum":["bytes"]},{"type":"string","enum":["string"]},{"type":"string","enum":["File"]},{"$ref":"#\/definitions\/CommandInputSchema"},{"$ref":"#\/definitions\/CommandInputMapSchema"},{"$ref":"#\/definitions\/CommandInputArraySchema"},{"$ref":"#\/definitions\/CommandInputEnumSchema"},{"$ref":"#\/definitions\/CommandInputRecordSchema"},{"type":"string"}]}}]},"___inputBinding":{"$ref":"#\/definitions\/CommandLineBinding"}},"required":["items","type"]}},{"$eref":{"type":"object","properties":{"___name":{"type":"string"},"___type":{"type":"string","enum":["enum"]},"___symbols":{"type":"array","items":{"type":"string"}},"___inputBinding":{"$ref":"#\/definitions\/CommandLineBinding"}},"required":["type","symbols","name"]}},{"$eref":{"type":"object","properties":{"___fields":{"type":"array","items":{"anyOf":[{"$ref":"#\/definitions\/CommandInputSchema"},{"$ref":"#\/definitions\/CommandInputArraySchema"},{"$ref":"#\/definitions\/CommandInputRecordSchema"},{"$ref":"#\/definitions\/CommandInputEnumSchema"},{"$ref":"#\/definitions\/CommandInputMapSchema"}]}},"___type":{"type":"string","enum":["record"]},"___inputBinding":{"$ref":"#\/definitions\/CommandLineBinding"}},"required":["type","fields"]}},{"type":"string"}]}}]},"___inputBinding":{"$eref":{"type":"object","properties":{"___itemSeparator":{"type":["string","null"]},"___loadContents":{"type":"boolean"},"___prefix":{"type":"string"},"___secondaryFiles":{"anyOf":[{"type":"string"},{"$ref":"#\/definitions\/Expression"},{"type":"array","items":{"anyOf":[{"type":"string"},{"$ref":"#\/definitions\/Expression"}]}}]},"___valueFrom":{"anyOf":[{"type":"string"},{"$ref":"#\/definitions\/Expression"}]},"___separate":{"type":"boolean"},"___position":{"type":"number"}}}}},"required":["items","type"]},"_88SBGRevision":{"type":"object","properties":{"___sbg:modifiedBy":{"type":"string"},"___sbg:revisionNotes":{"type":["string","null"]},"___sbg:revision":{"type":"number"},"___sbg:modifiedOn":{"type":"number"}},"required":["sbg:revision","sbg:modifiedBy","sbg:revisionNotes","sbg:modifiedOn"]},"_88CWLVersions":{"type":"string","enum":["sbg:draft-2"]},"_88CommandLineBinding":{"type":"object","properties":{"___itemSeparator":{"type":["string","null"]},"___loadContents":{"type":"boolean"},"___prefix":{"type":"string"},"___secondaryFiles":{"anyOf":[{"type":"string"},{"$eref":{"type":"object","properties":{"___script":{"type":"string"},"___class":{"type":"string","enum":["Expression"]},"___engine":{"type":"string"}},"required":["engine","script","class"]}},{"type":"array","items":{"anyOf":[{"type":"string"},{"$eref":{"type":"object","properties":{"___script":{"type":"string"},"___class":{"type":"string","enum":["Expression"]},"___engine":{"type":"string"}},"required":["engine","script","class"]}}]}}]},"___valueFrom":{"anyOf":[{"type":"string"},{"$eref":{"type":"object","properties":{"___script":{"type":"string"},"___class":{"type":"string","enum":["Expression"]},"___engine":{"type":"string"}},"required":["engine","script","class"]}}]},"___separate":{"type":"boolean"},"___position":{"type":"number"}}},"_88DockerRequirement":{"type":"object","properties":{"___dockerOutputDirectory":{"type":"string"},"___class":{"type":"string","enum":["DockerRequirement"]},"___dockerLoad":{"type":"string"},"___dockerFile":{"type":"string"},"___dockerPull":{"type":"string"},"___dockerImageId":{"type":"string"}},"required":["class"]},"_88CommandInputEnumSchema":{"type":"object","properties":{"___name":{"type":"string"},"___type":{"type":"string","enum":["enum"]},"___symbols":{"type":"array","items":{"type":"string"}},"___inputBinding":{"$eref":{"type":"object","properties":{"___itemSeparator":{"type":["string","null"]},"___loadContents":{"type":"boolean"},"___prefix":{"type":"string"},"___secondaryFiles":{"anyOf":[{"type":"string"},{"$ref":"#\/definitions\/Expression"},{"type":"array","items":{"anyOf":[{"type":"string"},{"$ref":"#\/definitions\/Expression"}]}}]},"___valueFrom":{"anyOf":[{"type":"string"},{"$ref":"#\/definitions\/Expression"}]},"___separate":{"type":"boolean"},"___position":{"type":"number"}}}}},"required":["type","symbols","name"]},"_88SubworkflowFeatureRequirement":{"type":"object","properties":{}},"_88FileDef":{"type":"object","properties":{"___fileContent":{"anyOf":[{"type":"string"},{"$eref":{"type":"object","properties":{"___script":{"type":"string"},"___class":{"type":"string","enum":["Expression"]},"___engine":{"type":"string"}},"required":["engine","script","class"]}}]},"___filename":{"anyOf":[{"type":"string"},{"$eref":{"type":"object","properties":{"___script":{"type":"string"},"___class":{"type":"string","enum":["Expression"]},"___engine":{"type":"string"}},"required":["engine","script","class"]}}]}},"required":["filename","fileContent"]},"_88CommandOutputSchema":{"type":"object","properties":{"___type":{"anyOf":[{"type":"string","enum":["null"]},{"type":"string","enum":["boolean"]},{"type":"string","enum":["int"]},{"type":"string","enum":["long"]},{"type":"string","enum":["float"]},{"type":"string","enum":["double"]},{"type":"string","enum":["bytes"]},{"type":"string","enum":["string"]},{"type":"string","enum":["File"]},{"$eref":{"type":"object","properties":{"___type":{"anyOf":[{"type":"string","enum":["null"]},{"type":"string","enum":["boolean"]},{"type":"string","enum":["int"]},{"type":"string","enum":["long"]},{"type":"string","enum":["float"]},{"type":"string","enum":["double"]},{"type":"string","enum":["bytes"]},{"type":"string","enum":["string"]},{"type":"string","enum":["File"]},{"$ref":"#\/definitions\/CommandOutputSchema"},{"type":"string"},{"$ref":"#\/definitions\/CommandOutputMapSchema"},{"$ref":"#\/definitions\/CommandOutputArraySchema"},{"$ref":"#\/definitions\/CommandOutputRecordSchema"},{"$ref":"#\/definitions\/CommandOutputEnumSchema"},{"type":"array","items":{"anyOf":[{"type":"string","enum":["null"]},{"type":"string","enum":["boolean"]},{"type":"string","enum":["int"]},{"type":"string","enum":["long"]},{"type":"string","enum":["float"]},{"type":"string","enum":["double"]},{"type":"string","enum":["bytes"]},{"type":"string","enum":["string"]},{"type":"string","enum":["File"]},{"$ref":"#\/definitions\/CommandOutputSchema"},{"type":"string"},{"$ref":"#\/definitions\/CommandOutputMapSchema"},{"$ref":"#\/definitions\/CommandOutputArraySchema"},{"$ref":"#\/definitions\/CommandOutputEnumSchema"},{"$ref":"#\/definitions\/CommandOutputRecordSchema"}]}}]},"___outputBinding":{"$ref":"#\/definitions\/CommandOutputBinding"}},"required":["type"]}},{"type":"string"},{"$eref":{"type":"object","properties":{"___type":{"type":"string","enum":["map"]},"___outputBinding":{"$ref":"#\/definitions\/CommandOutputBinding"},"___values":{"type":"string"}},"required":["type","values"]}},{"$eref":{"type":"object","properties":{"___type":{"type":"string","enum":["array"]},"___outputBinding":{"$ref":"#\/definitions\/CommandOutputBinding"},"___items":{"anyOf":[{"type":"string","enum":["null"]},{"type":"string","enum":["boolean"]},{"type":"string","enum":["int"]},{"type":"string","enum":["long"]},{"type":"string","enum":["float"]},{"type":"string","enum":["double"]},{"type":"string","enum":["bytes"]},{"type":"string","enum":["string"]},{"type":"string","enum":["File"]},{"$ref":"#\/definitions\/CommandOutputSchema"},{"$ref":"#\/definitions\/CommandOutputMapSchema"},{"$ref":"#\/definitions\/CommandOutputArraySchema"},{"$ref":"#\/definitions\/CommandOutputRecordSchema"},{"$ref":"#\/definitions\/CommandOutputEnumSchema"},{"type":"string"},{"type":"array","items":{"anyOf":[{"type":"string","enum":["null"]},{"type":"string","enum":["boolean"]},{"type":"string","enum":["int"]},{"type":"string","enum":["long"]},{"type":"string","enum":["float"]},{"type":"string","enum":["double"]},{"type":"string","enum":["bytes"]},{"type":"string","enum":["string"]},{"type":"string","enum":["File"]},{"$ref":"#\/definitions\/CommandOutputSchema"},{"$ref":"#\/definitions\/CommandOutputMapSchema"},{"$ref":"#\/definitions\/CommandOutputArraySchema"},{"$ref":"#\/definitions\/CommandOutputEnumSchema"},{"$ref":"#\/definitions\/CommandOutputRecordSchema"},{"type":"string"}]}}]}},"required":["items","type"]}},{"$eref":{"type":"object","properties":{"___fields":{"type":"array","items":{"anyOf":[{"$ref":"#\/definitions\/CommandOutputSchema"},{"$ref":"#\/definitions\/CommandOutputArraySchema"},{"$ref":"#\/definitions\/CommandOutputRecordSchema"},{"$ref":"#\/definitions\/CommandOutputEnumSchema"},{"$ref":"#\/definitions\/CommandOutputMapSchema"}]}},"___type":{"type":"string","enum":["record"]},"___outputBinding":{"$ref":"#\/definitions\/CommandOutputBinding"}},"required":["type","fields"]}},{"$eref":{"type":"object","properties":{"___type":{"type":"string","enum":["enum"]},"___outputBinding":{"$ref":"#\/definitions\/CommandOutputBinding"},"___symbols":{"type":"array","items":{"type":"string"}}},"required":["type","symbols"]}},{"type":"array","items":{"anyOf":[{"type":"string","enum":["null"]},{"type":"string","enum":["boolean"]},{"type":"string","enum":["int"]},{"type":"string","enum":["long"]},{"type":"string","enum":["float"]},{"type":"string","enum":["double"]},{"type":"string","enum":["bytes"]},{"type":"string","enum":["string"]},{"type":"string","enum":["File"]},{"$eref":{"type":"object","properties":{"___type":{"anyOf":[{"type":"string","enum":["null"]},{"type":"string","enum":["boolean"]},{"type":"string","enum":["int"]},{"type":"string","enum":["long"]},{"type":"string","enum":["float"]},{"type":"string","enum":["double"]},{"type":"string","enum":["bytes"]},{"type":"string","enum":["string"]},{"type":"string","enum":["File"]},{"$ref":"#\/definitions\/CommandOutputSchema"},{"type":"string"},{"$ref":"#\/definitions\/CommandOutputMapSchema"},{"$ref":"#\/definitions\/CommandOutputArraySchema"},{"$ref":"#\/definitions\/CommandOutputRecordSchema"},{"$ref":"#\/definitions\/CommandOutputEnumSchema"},{"type":"array","items":{"anyOf":[{"type":"string","enum":["null"]},{"type":"string","enum":["boolean"]},{"type":"string","enum":["int"]},{"type":"string","enum":["long"]},{"type":"string","enum":["float"]},{"type":"string","enum":["double"]},{"type":"string","enum":["bytes"]},{"type":"string","enum":["string"]},{"type":"string","enum":["File"]},{"$ref":"#\/definitions\/CommandOutputSchema"},{"type":"string"},{"$ref":"#\/definitions\/CommandOutputMapSchema"},{"$ref":"#\/definitions\/CommandOutputArraySchema"},{"$ref":"#\/definitions\/CommandOutputEnumSchema"},{"$ref":"#\/definitions\/CommandOutputRecordSchema"}]}}]},"___outputBinding":{"$ref":"#\/definitions\/CommandOutputBinding"}},"required":["type"]}},{"type":"string"},{"$eref":{"type":"object","properties":{"___type":{"type":"string","enum":["map"]},"___outputBinding":{"$ref":"#\/definitions\/CommandOutputBinding"},"___values":{"type":"string"}},"required":["type","values"]}},{"$eref":{"type":"object","properties":{"___type":{"type":"string","enum":["array"]},"___outputBinding":{"$ref":"#\/definitions\/CommandOutputBinding"},"___items":{"anyOf":[{"type":"string","enum":["null"]},{"type":"string","enum":["boolean"]},{"type":"string","enum":["int"]},{"type":"string","enum":["long"]},{"type":"string","enum":["float"]},{"type":"string","enum":["double"]},{"type":"string","enum":["bytes"]},{"type":"string","enum":["string"]},{"type":"string","enum":["File"]},{"$ref":"#\/definitions\/CommandOutputSchema"},{"$ref":"#\/definitions\/CommandOutputMapSchema"},{"$ref":"#\/definitions\/CommandOutputArraySchema"},{"$ref":"#\/definitions\/CommandOutputRecordSchema"},{"$ref":"#\/definitions\/CommandOutputEnumSchema"},{"type":"string"},{"type":"array","items":{"anyOf":[{"type":"string","enum":["null"]},{"type":"string","enum":["boolean"]},{"type":"string","enum":["int"]},{"type":"string","enum":["long"]},{"type":"string","enum":["float"]},{"type":"string","enum":["double"]},{"type":"string","enum":["bytes"]},{"type":"string","enum":["string"]},{"type":"string","enum":["File"]},{"$ref":"#\/definitions\/CommandOutputSchema"},{"$ref":"#\/definitions\/CommandOutputMapSchema"},{"$ref":"#\/definitions\/CommandOutputArraySchema"},{"$ref":"#\/definitions\/CommandOutputEnumSchema"},{"$ref":"#\/definitions\/CommandOutputRecordSchema"},{"type":"string"}]}}]}},"required":["items","type"]}},{"$eref":{"type":"object","properties":{"___type":{"type":"string","enum":["enum"]},"___outputBinding":{"$ref":"#\/definitions\/CommandOutputBinding"},"___symbols":{"type":"array","items":{"type":"string"}}},"required":["type","symbols"]}},{"$eref":{"type":"object","properties":{"___fields":{"type":"array","items":{"anyOf":[{"$ref":"#\/definitions\/CommandOutputSchema"},{"$ref":"#\/definitions\/CommandOutputArraySchema"},{"$ref":"#\/definitions\/CommandOutputRecordSchema"},{"$ref":"#\/definitions\/CommandOutputEnumSchema"},{"$ref":"#\/definitions\/CommandOutputMapSchema"}]}},"___type":{"type":"string","enum":["record"]},"___outputBinding":{"$ref":"#\/definitions\/CommandOutputBinding"}},"required":["type","fields"]}}]}}]},"___outputBinding":{"$eref":{"type":"object","properties":{"___glob":{"anyOf":[{"type":"string"},{"$ref":"#\/definitions\/Expression"},{"type":"array","items":{"type":"string"}}]},"___loadContents":{"type":"boolean"},"___outputEval":{"$ref":"#\/definitions\/Expression"},"___secondaryFiles":{"anyOf":[{"type":"string"},{"$ref":"#\/definitions\/Expression"},{"type":"array","items":{"anyOf":[{"type":"string"},{"$ref":"#\/definitions\/Expression"}]}}]},"___sbg:metadata":{"additionalProperties":{"anyOf":[{"type":"string"},{"$ref":"#\/definitions\/Expression"}]},"type":"object"},"___sbg:inheritMetadataFrom":{"type":"string"}}}}},"required":["type"]},"_88CommandInputMapSchema":{"type":"object","properties":{"___type":{"type":"string","enum":["map"]},"___inputBinding":{"$eref":{"type":"object","properties":{"___itemSeparator":{"type":["string","null"]},"___loadContents":{"type":"boolean"},"___prefix":{"type":"string"},"___secondaryFiles":{"anyOf":[{"type":"string"},{"$ref":"#\/definitions\/Expression"},{"type":"array","items":{"anyOf":[{"type":"string"},{"$ref":"#\/definitions\/Expression"}]}}]},"___valueFrom":{"anyOf":[{"type":"string"},{"$ref":"#\/definitions\/Expression"}]},"___separate":{"type":"boolean"},"___position":{"type":"number"}}}},"___values":{"type":"string"}},"required":["type","values"]},"_88SBGLink":{"type":"object","properties":{"___id":{"type":"string"},"___label":{"type":"string"}},"required":["label","id"]}},"properties":{"___requirements":{"type":"array","items":{"anyOf":[{"$eref":{"type":"object","properties":{"___dockerOutputDirectory":{"type":"string"},"___class":{"type":"string","enum":["DockerRequirement"]},"___dockerLoad":{"type":"string"},"___dockerFile":{"type":"string"},"___dockerPull":{"type":"string"},"___dockerImageId":{"type":"string"}},"required":["class"]}},{"$eref":{"type":"object","properties":{}}},{"$eref":{"type":"object","properties":{"___fileDef":{"type":"array","items":{"$ref":"#\/definitions\/FileDef"}},"___class":{"type":"string","enum":["CreateFileRequirement"]}},"required":["class","fileDef"]}},{"$eref":{"type":"object","properties":{}}},{"$eref":{"type":"object","properties":{}}},{"$eref":{"type":"object","properties":{}}},{"$eref":{"type":"object","properties":{"___requirements":{"type":"array","items":{"anyOf":[{"$ref":"#\/definitions\/DockerRequirement"},{"$ref":"#\/definitions\/SubworkflowFeatureRequirement"},{"$ref":"#\/definitions\/CreateFileRequirement"},{"$ref":"#\/definitions\/EnvVarRequirement"},{"$ref":"#\/definitions\/ScatterFeatureRequirement"},{"$ref":"#\/definitions\/SchemaDefRequirement"},{"$ref":"#\/definitions\/ExpressionEngineRequirement"}]}},"___class":{"type":"string","enum":["ExpressionEngineRequirement"]},"___engineCommand":{"anyOf":[{"type":"string"},{"type":"array","items":{"type":"string"}}]},"___id":{"type":"string"},"___engineConfig":{"type":"array","items":{"type":"string"}}},"required":["class","id"]}}]}},"___sbg:modifiedBy":{"type":"string"},"___sbg:validationErrors":{"type":"array","items":{"type":"string"}},"___sbg:modifiedOn":{"type":"number"},"___successCodes":{"type":"array","items":{"type":"number"}},"___stdin":{"anyOf":[{"type":"string"},{"$eref":{"type":"object","properties":{"___script":{"type":"string"},"___class":{"type":"string","enum":["Expression"]},"___engine":{"type":"string"}},"required":["engine","script","class"]}}]},"___arguments":{"type":"array","items":{"anyOf":[{"type":"string"},{"$eref":{"type":"object","properties":{"___itemSeparator":{"type":["string","null"]},"___loadContents":{"type":"boolean"},"___prefix":{"type":"string"},"___secondaryFiles":{"anyOf":[{"type":"string"},{"$ref":"#\/definitions\/Expression"},{"type":"array","items":{"anyOf":[{"type":"string"},{"$ref":"#\/definitions\/Expression"}]}}]},"___valueFrom":{"anyOf":[{"type":"string"},{"$ref":"#\/definitions\/Expression"}]},"___separate":{"type":"boolean"},"___position":{"type":"number"}}}}]}},"___sbg:license":{"type":"string"},"___description":{"type":"string"},"___sbg:toolkit":{"type":"string"},"___class":{"type":"string","enum":["CommandLineTool"]},"___temporaryFailCodes":{"type":"array","items":{"type":"number"}},"___sbg:links":{"type":"array","items":{"$eref":{"type":"object","properties":{"___id":{"type":"string"},"___label":{"type":"string"}},"required":["label","id"]}}},"___sbg:contributors":{"type":"array","items":{"type":"string"}},"___sbg:sbgMaintained":{"type":"boolean"},"___sbg:revisionInfo":{"type":"array","items":{"$eref":{"type":"object","properties":{"___sbg:modifiedBy":{"type":"string"},"___sbg:revisionNotes":{"type":["string","null"]},"___sbg:revision":{"type":"number"},"___sbg:modifiedOn":{"type":"number"}},"required":["sbg:revision","sbg:modifiedBy","sbg:revisionNotes","sbg:modifiedOn"]}}},"___sbg:project":{"type":"string"},"___sbg:revision":{"type":"number"},"___sbg:id":{"type":"string"},"___hints":{"type":"array","items":{}},"___label":{"type":"string"},"___sbg:categories":{"type":"array","items":{"type":"string"}},"___sbg:toolAuthor":{"type":"string"},"___cwlVersion":{"$eref":{"type":"string","enum":["sbg:draft-2"]},"description":"CWL document version"},"___outputs":{"type":"array","items":{"$eref":{"type":"object","properties":{"___streamable":{"type":"boolean"},"___description":{"type":"string"},"___type":{"anyOf":[{"type":"string","enum":["null"]},{"type":"string","enum":["boolean"]},{"type":"string","enum":["int"]},{"type":"string","enum":["long"]},{"type":"string","enum":["float"]},{"type":"string","enum":["double"]},{"type":"string","enum":["bytes"]},{"type":"string","enum":["string"]},{"type":"string","enum":["File"]},{"$ref":"#\/definitions\/CommandOutputSchema"},{"type":"string"},{"type":"array","items":{"anyOf":[{"type":"string","enum":["null"]},{"type":"string","enum":["boolean"]},{"type":"string","enum":["int"]},{"type":"string","enum":["long"]},{"type":"string","enum":["float"]},{"type":"string","enum":["double"]},{"type":"string","enum":["bytes"]},{"type":"string","enum":["string"]},{"type":"string","enum":["File"]},{"$ref":"#\/definitions\/CommandOutputSchema"},{"type":"string"}]}}]},"___outputBinding":{"$ref":"#\/definitions\/CommandOutputBinding"},"___default":{},"___id":{"type":"string"},"___label":{"type":"string"},"___sbg:fileTypes":{"type":"string"}},"required":["id"]}}},"___sbg:createdBy":{"type":"string"},"___sbg:revisionNotes":{"type":["string","null"]},"___baseCommand":{"anyOf":[{"type":"string"},{"$eref":{"type":"object","properties":{"___script":{"type":"string"},"___class":{"type":"string","enum":["Expression"]},"___engine":{"type":"string"}},"required":["engine","script","class"]}},{"type":"array","items":{"anyOf":[{"type":"string"},{"$eref":{"type":"object","properties":{"___script":{"type":"string"},"___class":{"type":"string","enum":["Expression"]},"___engine":{"type":"string"}},"required":["engine","script","class"]}}]}}]},"___sbg:toolkitVersion":{"type":"string"},"___stdout":{"anyOf":[{"type":"string"},{"$eref":{"type":"object","properties":{"___script":{"type":"string"},"___class":{"type":"string","enum":["Expression"]},"___engine":{"type":"string"}},"required":["engine","script","class"]}}]},"___permanentFailCodes":{"type":"array","items":{"type":"number"}},"___inputs":{"type":"array","items":{"$eref":{"type":"object","properties":{"___streamable":{"type":"boolean"},"___description":{"type":"string"},"___type":{"anyOf":[{"type":"string","enum":["null"]},{"type":"string","enum":["boolean"]},{"type":"string","enum":["int"]},{"type":"string","enum":["long"]},{"type":"string","enum":["float"]},{"type":"string","enum":["double"]},{"type":"string","enum":["bytes"]},{"type":"string","enum":["string"]},{"type":"string","enum":["File"]},{"$ref":"#\/definitions\/CommandInputSchema"},{"$ref":"#\/definitions\/CommandInputArraySchema"},{"$ref":"#\/definitions\/CommandInputMapSchema"},{"$ref":"#\/definitions\/CommandInputEnumSchema"},{"$ref":"#\/definitions\/CommandInputRecordSchema"},{"type":"string"},{"type":"array","items":{"anyOf":[{"type":"string","enum":["null"]},{"type":"string","enum":["boolean"]},{"type":"string","enum":["int"]},{"type":"string","enum":["long"]},{"type":"string","enum":["float"]},{"type":"string","enum":["double"]},{"type":"string","enum":["bytes"]},{"type":"string","enum":["string"]},{"type":"string","enum":["File"]},{"$ref":"#\/definitions\/CommandInputSchema"},{"$ref":"#\/definitions\/CommandInputArraySchema"},{"$ref":"#\/definitions\/CommandInputMapSchema"},{"$ref":"#\/definitions\/CommandInputEnumSchema"},{"$ref":"#\/definitions\/CommandInputRecordSchema"},{"type":"string"}]}}]},"___inputBinding":{"$ref":"#\/definitions\/CommandLineBinding"},"___default":{},"___sbg:category":{"type":"string"},"___id":{"type":"string"},"___label":{"type":"string"},"___sbg:fileTypes":{"type":"string"}},"required":["id"]}}},"___id":{"type":"string"}},"required":["inputs","outputs","class"]}