{"allOf":[{"$eref":{"x-sdk-model":"job","additionalProperties":false,"type":"object","properties":{"___destination":{"$ref":"#\/definitions\/destination"},"___gear_id":{"$ref":"#\/definitions\/gear_id"},"___config":{"$ref":"#\/definitions\/config"},"___tags":{"$ref":"#\/definitions\/tags"},"___inputs":{"$ref":"#\/definitions\/inputs-object"}},"required":["gear_id"]}}],"$schema":"http:\/\/json-schema.org\/draft-04\/schema#","type":"object","example":{"inputs":{"dicom":{"name":"1_1_dicom.zip","id":"573c9e6a844eac7fc01747cd","type":"acquisition"}},"destination":{"id":"573c9e6a844eac7fc01747cd","type":"acquisition"},"gear_id":"aex","config":{"two-digit multiple of ten":20},"tags":["ad-hoc"]}}