{"$schema":"http:\/\/json-schema.org\/draft-04\/schema#","description":"Beschreibung fehlt","title":"Root schema.","type":"object","properties":{"___Info":{"description":"Beschreibung fehlt","title":"Info (Beschreibung)","type":"string"},"___Zielgruppe":{"description":"Beschreibung fehlt","title":"Zielgruppe","type":"string"},"___Kategorie":{"description":"Beschreibung fehlt","title":"Kategorie","type":"array","items":{"type":"string"}},"___Veranstalter":{"description":"Beschreibung fehlt","title":"Veranstalter","type":"string"},"___Link_Text":{"description":"Beschreibung fehlt","title":"Link Text","type":"string"}}}