{"$schema":"http:\/\/json-schema.org\/draft-04\/schema#","type":"object","properties":{"___location":{"oneOf":[{"type":"object","properties":{"___type":{"type":"string","enum":["http:\/\/schema.org\/Place","http:\/\/schema.org\/PostalAddress"]}}},{"type":"string"}]},"___capacity":{"oneOf":[{"type":"integer"}]},"___topic":{"oneOf":[{"format":"uri","type":"string"},{"type":"array","items":{"format":"uri","type":"string"}}]},"___accreditation":{"oneOf":[{"type":"string"},{"type":"object","properties":{"___type":{"type":"string","enum":["http:\/\/schema.org\/Organization"]}}}]},"___startDate":{"oneOf":[{"format":"date","type":"string"}]},"___endDate":{"oneOf":[{"format":"date","type":"string"}]},"___alternateName":{"oneOf":[{"type":"string"}]},"___targetAudience":{"oneOf":[{"format":"uri","type":"string"},{"type":"array","items":{"format":"uri","type":"string"}}]},"___prerequisite":{"oneOf":[{"type":"string"},{"type":"array","items":{"type":"string"}}]},"___contact":{"oneOf":[{"type":"object","properties":{"___type":{"type":"string","enum":["http:\/\/schema.org\/Organization","http:\/\/schema.org\/Person"]}},"required":["properties","type"]},{"type":"array","items":{"type":"object","properties":{"___type":{"type":"string","enum":["http:\/\/schema.org\/Organization","http:\/\/schema.org\/Person"]}},"required":["properties","type"]}}]},"___name":{"oneOf":[{"type":"string"},{"type":"array","items":{"type":"string"}}]},"___programme":{"oneOf":[{"type":"string"},{"format":"uri","type":"string"}]},"___description":{"oneOf":[{"type":"string"},{"type":"array","items":{"type":"string"}}]},"___eligibility":{"oneOf":[{"type":"string"},{"type":"array","items":{"type":"string"}},{"type":"string","enum":["First come first served","Registration of interest","By invitation"]},{"type":"array","items":{"type":"string","enum":["First come first served","Meetings and conferences","By invitation"]}}]},"___url":{"oneOf":[{"format":"uri","type":"string"}]},"___hostInstitution":{"oneOf":[{"type":"object","properties":{"___type":{"type":"string","enum":["http:\/\/schema.org\/Organization"]}}},{"type":"array","items":{"type":"object","properties":{"___type":{"type":"string","enum":["http:\/\/schema.org\/Organization"]}}}}]},"___keywords":{"oneOf":[{"type":"string"},{"type":"array","items":{"type":"string"}}]},"___deadline":{"oneOf":[{"type":"string"},{"type":"array","items":{"type":"string"}}]},"___eventType":{"oneOf":[{"type":"string","enum":["Workshops and courses","Meetings and conferences","Receptions and networking","Awards and prizegivings"]},{"type":"array","items":{"type":"string","enum":["Workshops and courses","Meetings and conferences","Receptions and networking","Awards and prizegivings"]}}]}},"required":["startDate","endDate","name","description","location","contact","hostInstitution","eventType"],"recommended":["url","keywords","topic","targetAudience","programme","deadline","prerequisite","capacity","eligibility","alternateName","accreditation"]}