{"$schema":"http:\/\/json-schema.org\/draft-04\/schema#","description":"Schema for spreadsheet configuration description","id":"#","additionalProperties":false,"type":"object","properties":{"___sheet_config":{"pattern":"^active|name:.+|first|last$","type":["integer","string"],"minimum":1},"___headers_index_config":{"type":"object","properties":{"___column_index":{"$eref":{"type":"object","properties":{"___first":{"pattern":"^automatic$","type":["integer","string"],"minimum":1},"___last":{"pattern":"^automatic|severalEmptyCells:[0-9]+$","type":["integer","string"],"minimum":1}},"required":["first","last"]}},"___row_index":{"$eref":{"type":"object","properties":{"___first":{"pattern":"^automatic$","type":["integer","string"],"minimum":1},"___last":{"pattern":"^automatic|severalEmptyCells:[0-9]+$","type":["integer","string"],"minimum":1}},"required":["first","last"]}}},"required":["row_index","column_index"]},"___data_type_config":{"minItems":1,"definitions_type":{"date":{"additionalProperties":false,"properties":{"___base":{"enum":["date"]}},"required":["base"]},"string":{"additionalProperties":false,"properties":{"___base":{"enum":["string"]},"___filter_pattern":{"type":"string"},"___convert_numbers":{"type":"boolean"},"___pattern":{"type":"string"}},"required":["base"]},"automatic":{"additionalProperties":false,"properties":{"___base":{"enum":["automatic"]}},"required":["base"]},"integer":{"additionalProperties":false,"properties":{"___base":{"enum":["integer"]},"___minimum":{"type":"integer"},"___maximum":{"type":"integer"}},"required":["base"]},"float":{"additionalProperties":false,"properties":{"___base":{"enum":["float"]},"___minimum":{"type":"number"},"___maximum":{"type":"number"}},"required":["base"]},"enum":{"_8_required":["base","enum_values"],"_8_additionalProperties":false,"_8_properties":{"_8_filter":{"_8_type":"object","_8_required":["whitelist_values"],"_8_additionalProperties":false,"_8_properties":{"_8_whitelist_values":{"_8_type":"array","_8_uniqueItems":true,"_8_minItems":1,"_8_items":{"_8_type":"string"}}}},"_8_enum_values":{"_8_type":"array","_8_uniqueItems":true,"_8_minItems":1,"_8_items":{"_8_type":"string"}},"_8_base":{"_8_enum":["enum"]}}}},"type":"array","items":{"additionalProperties":false,"type":"object","properties":{"___type":{"oneOf":[{"$eref":{"additionalProperties":false,"properties":{"___base":{"enum":["automatic"]}},"required":["base"]}},{"$eref":{"additionalProperties":false,"properties":{"___base":{"enum":["date"]}},"required":["base"]}},{"$eref":{"additionalProperties":false,"properties":{"___base":{"enum":["enum"]},"___filter":{"additionalProperties":false,"type":"object","properties":{"___whitelist_values":{"minItems":1,"uniqueItems":true,"type":"array","items":{"type":"string"}}},"required":["whitelist_values"]},"___enum_values":{"minItems":1,"uniqueItems":true,"type":"array","items":{"type":"string"}}},"required":["base","enum_values"]}},{"$eref":{"additionalProperties":false,"properties":{"___base":{"enum":["float"]},"___minimum":{"type":"number"},"___maximum":{"type":"number"}},"required":["base"]}},{"$eref":{"additionalProperties":false,"properties":{"___base":{"enum":["integer"]},"___minimum":{"type":"integer"},"___maximum":{"type":"integer"}},"required":["base"]}},{"$eref":{"additionalProperties":false,"properties":{"___base":{"enum":["string"]},"___filter_pattern":{"type":"string"},"___convert_numbers":{"type":"boolean"},"___pattern":{"type":"string"}},"required":["base"]}}]},"___fail_on_empty_cell":{"type":"boolean"},"___header":{"type":"string"},"___fail_on_type_error":{"type":"boolean"},"___fail_on_header_not_found":{"type":"boolean"}},"required":["header"]}},"___definitions_index":{"type":"object","properties":{"___first":{"pattern":"^automatic$","type":["integer","string"],"minimum":1},"___last":{"pattern":"^automatic|severalEmptyCells:[0-9]+$","type":["integer","string"],"minimum":1}},"required":["first","last"]},"___data_index_config":{"type":"object","properties":{"___column_index":{"$eref":{"type":"object","properties":{"___first":{"pattern":"^automatic$","type":["integer","string"],"minimum":1},"___last":{"pattern":"^automatic|severalEmptyCells:[0-9]+$","type":["integer","string"],"minimum":1}},"required":["first","last"]}},"___row_index":{"$eref":{"type":"object","properties":{"___first":{"pattern":"^automatic$","type":["integer","string"],"minimum":1},"___last":{"pattern":"^automatic|severalEmptyCells:[0-9]+$","type":["integer","string"],"minimum":1}},"required":["first","last"]}}},"required":["row_index","column_index"]},"___filter_properties":{"additionalProperties":false,"type":"object","properties":{"___excluded_fail_on_empty_cell":{"type":"boolean"},"___excluded_fail_on_type_error":{"type":"boolean"},"___excluded_enable_logging":{"type":"boolean"}}},"___orientation":{"pattern":"^column_based|row_based$","type":"string"}},"required":["orientation","headers_index_config","data_index_config","data_type_config"]}