{"$schema":"http:\/\/json-schema.org\/draft-04\/schema#","additionalProperties":false,"type":"object","properties":{"___repositories":{"patternProperties":{"___.*":{"description":"Initialized repositories","type":"object","properties":{"___identity-file":{"description":"SSH private key file for deploy","type":"string"},"___ssh-alias":{"description":"SSH alias to connect to the repository","type":"string"}},"required":["identity-file","ssh-alias"]}},"description":"Already configured repositories. A hash of repository names (keys) and configured settings (values)","additionalProperties":false,"type":"object"},"___applications":{"patternProperties":{"___.*":{"description":"Application settings","additionalProperties":false,"type":"object","properties":{"___overrides":{"description":"Overrides for the applications .cliconfig.json","type":"object"},"___archive-url":{"description":"Optional url where the application archive was downloaded","type":"string"},"___cliconfig-override":{"description":"Overrides cliconfig with a file from another directory","type":"string"},"___repository":{"type":"string"}}}},"description":"Links application names (keys) to settings (values)","additionalProperties":false,"type":"object"},"___config":{"description":"Clic options","additionalProperties":false,"type":"object","properties":{"___ssh-dir":{"default":"$HOME\/.ssh","description":" Path to .ssh directory, to store generated keys and change ssh configuration","type":"string"},"___applications-dir":{"default":"$HOME\/apps","description":"Path to the applications directory","type":"string"},"___vhosts-dir":{"default":"$HOME\/public_html","description":"Path to the vhosts directory","type":"string"},"___clic-dir":{"default":"$HOME\/.clic","description":"Path to directory where clic stores its files","type":"string"}}},"___global-vars":{"patternProperties":{"___^[a-zA-Z_][a-zA-Z_0-9]*$":{"type":"string"}},"description":"This is a hash of variable names (keys) and values (values).","type":"object"},"___vhosts":{"patternProperties":{"___.*":{"description":"Vhost settings","additionalProperties":false,"type":"object","properties":{"___disabled":{"default":false,"type":"boolean"},"___application":{"type":"string"}},"required":["application"]}},"description":"Links a vhost name (keys) to settings (values)","additionalProperties":false,"type":"object"}},"required":["config"]}