{"esriDocumentation":{"examples":[{"code":{"symbolLayers":[{"outline":{"size":1,"color":[0,0,0]},"size":12,"material":{"color":[255,255,255]},"resource":{"primitive":"kite"},"anchor":"bottom","type":"Icon"}]},"title":"Icon SymbolLayer"}]},"$schema":"http:\/\/json-schema.org\/draft-04\/schema","description":"IconSymbol3DLayer is used to render Point geometries using a flat 2D icon (e.g. a circle) with a PointSymbol3D in a SceneView.","additionalProperties":false,"title":"IconSymbol3DLayer","type":"object","properties":{"___material":{"$eref":{"esriDocumentation":{"examples":[{"code":{"material":{"color":[255,0,0],"transparency":20,"colorMixMode":"tint"}},"title":"material"}]},"$schema":"http:\/\/json-schema.org\/draft-04\/schema","description":"The material used to shade the geometry.","additionalProperties":false,"title":"Material","type":"object","properties":{"___color":{"$ref":"color_schema.json"},"___colorMixMode":{"default":"tint","description":"Controls how symbolLayer or visualVariable color is applied onto the underlying geometry color\/texture. This property only applies to FillSymbol3DLayer within MeshSymbol3D.<br><ul><li>`tint`: the feature's appearance (in terms of color) should be altered to match the symbol \/ visual variable color.<\/li><li>`replace`: the feature's color is replaced with the symbol \/ visual variable color.<\/li><li>`multiply`: the feature's color is multiplied with the symbol color.<\/li><\/ul>","type":"string","enum":["tint","replace","multiply"]},"___transparency":{"maximum":100,"type":"integer","minimum":0}}}},"___anchor":{"default":"center","type":"string","enum":["center","left","right","top","bottom","topLeft","topRight","bottomLeft","bottomRight"]},"___type":{"description":"Specifies the type of symbol used.","type":"string","enum":["Icon"]},"___outline":{"$eref":{"$schema":"http:\/\/json-schema.org\/draft-04\/schema","description":"The outline of the symbol layer.","additionalProperties":false,"title":"Outline","type":"object","properties":{"___color":{"$ref":"color_schema.json"},"___size":{"description":"Outline size in points, positive only","type":"number","minimum":0},"___transparency":{"description":"The value has to lie between `100` (full transparency) and `0` (full opacity).","maximum":100,"type":"integer","minimum":0}},"required":["color","size"]}},"___enable":{"type":"boolean"},"___size":{"description":"Icon size in points, positive only","type":"number","minimum":0},"___resource":{"$eref":{"oneOf":[{"required":["primitive"]},{"required":["href"]},{"required":["dataURI"]}],"$schema":"http:\/\/json-schema.org\/draft-04\/schema","description":"The shape (primitive) or image URL (href) used to visualize the features.","additionalProperties":false,"title":"IconSymbol3DLayer Resource","type":"object","properties":{"___href":{"oneOf":[{"pattern":"^https?:\/\/.+$","description":"An absolute URL","type":"string"},{"pattern":"^\\.\/.+$","description":"A relative path starting with .\/","type":"string"}],"description":"URL to the returned image."},"___primitive":{"description":"Specifies the type of symbol used.","type":"string","enum":["circle","square","cross","x","kite"]},"___dataURI":{"pattern":"^data:image\/(.|\\n|\\r)+$","description":"an image encoded as base64 string, starting with `data:image\/`","type":"string"}}}}},"required":["size","type"]}